[
  {
    "v": 1,
    "tokens": [
      {
        "form": "Τεκνία",
        "lemma": "τεκνίον",
        "pos": "N-",
        "morph": "----VPN-"
      },
      {
        "form": "μου,",
        "lemma": "ἐγώ",
        "pos": "RP",
        "morph": "----GS--"
      },
      {
        "form": "ταῦτα",
        "lemma": "οὗτος",
        "pos": "RD",
        "morph": "----APN-"
      },
      {
        "form": "γράφω",
        "lemma": "γράφω",
        "pos": "V-",
        "morph": "1PAI-S--"
      },
      {
        "form": "ὑμῖν",
        "lemma": "σύ",
        "pos": "RP",
        "morph": "----DP--"
      },
      {
        "form": "ἵνα",
        "lemma": "ἵνα",
        "pos": "C-",
        "morph": "--------"
      },
      {
        "form": "μὴ",
        "lemma": "μή",
        "pos": "D-",
        "morph": "--------"
      },
      {
        "form": "ἁμάρτητε.",
        "lemma": "ἁμαρτάνω",
        "pos": "V-",
        "morph": "2AAS-P--"
      },
      {
        "form": "καὶ",
        "lemma": "καί",
        "pos": "C-",
        "morph": "--------"
      },
      {
        "form": "ἐάν",
        "lemma": "ἐάν",
        "pos": "C-",
        "morph": "--------"
      },
      {
        "form": "τις",
        "lemma": "τις",
        "pos": "RI",
        "morph": "----NSM-"
      },
      {
        "form": "ἁμάρτῃ,",
        "lemma": "ἁμαρτάνω",
        "pos": "V-",
        "morph": "3AAS-S--"
      },
      {
        "form": "παράκλητον",
        "lemma": "παράκλητος",
        "pos": "N-",
        "morph": "----ASM-"
      },
      {
        "form": "ἔχομεν",
        "lemma": "ἔχω",
        "pos": "V-",
        "morph": "1PAI-P--"
      },
      {
        "form": "πρὸς",
        "lemma": "πρός",
        "pos": "P-",
        "morph": "--------"
      },
      {
        "form": "τὸν",
        "lemma": "ὁ",
        "pos": "RA",
        "morph": "----ASM-"
      },
      {
        "form": "πατέρα",
        "lemma": "πατήρ",
        "pos": "N-",
        "morph": "----ASM-"
      },
      {
        "form": "Ἰησοῦν",
        "lemma": "Ἰησοῦς",
        "pos": "N-",
        "morph": "----ASM-"
      },
      {
        "form": "Χριστὸν",
        "lemma": "Χριστός",
        "pos": "N-",
        "morph": "----ASM-"
      },
      {
        "form": "δίκαιον,",
        "lemma": "δίκαιος",
        "pos": "A-",
        "morph": "----ASM-"
      }
    ]
  },
  {
    "v": 2,
    "tokens": [
      {
        "form": "καὶ",
        "lemma": "καί",
        "pos": "C-",
        "morph": "--------"
      },
      {
        "form": "αὐτὸς",
        "lemma": "αὐτός",
        "pos": "RP",
        "morph": "----NSM-"
      },
      {
        "form": "ἱλασμός",
        "lemma": "ἱλασμός",
        "pos": "N-",
        "morph": "----NSM-"
      },
      {
        "form": "ἐστιν",
        "lemma": "εἰμί",
        "pos": "V-",
        "morph": "3PAI-S--"
      },
      {
        "form": "περὶ",
        "lemma": "περί",
        "pos": "P-",
        "morph": "--------"
      },
      {
        "form": "τῶν",
        "lemma": "ὁ",
        "pos": "RA",
        "morph": "----GPF-"
      },
      {
        "form": "ἁμαρτιῶν",
        "lemma": "ἁμαρτία",
        "pos": "N-",
        "morph": "----GPF-"
      },
      {
        "form": "ἡμῶν,",
        "lemma": "ἐγώ",
        "pos": "RP",
        "morph": "----GP--"
      },
      {
        "form": "οὐ",
        "lemma": "οὐ",
        "pos": "D-",
        "morph": "--------"
      },
      {
        "form": "περὶ",
        "lemma": "περί",
        "pos": "P-",
        "morph": "--------"
      },
      {
        "form": "τῶν",
        "lemma": "ὁ",
        "pos": "RA",
        "morph": "----GPF-"
      },
      {
        "form": "ἡμετέρων",
        "lemma": "ἡμέτερος",
        "pos": "A-",
        "morph": "----GPF-"
      },
      {
        "form": "δὲ",
        "lemma": "δέ",
        "pos": "C-",
        "morph": "--------"
      },
      {
        "form": "μόνον",
        "lemma": "μόνος",
        "pos": "A-",
        "morph": "----ASN-"
      },
      {
        "form": "ἀλλὰ",
        "lemma": "ἀλλά",
        "pos": "C-",
        "morph": "--------"
      },
      {
        "form": "καὶ",
        "lemma": "καί",
        "pos": "D-",
        "morph": "--------"
      },
      {
        "form": "περὶ",
        "lemma": "περί",
        "pos": "P-",
        "morph": "--------"
      },
      {
        "form": "ὅλου",
        "lemma": "ὅλος",
        "pos": "A-",
        "morph": "----GSM-"
      },
      {
        "form": "τοῦ",
        "lemma": "ὁ",
        "pos": "RA",
        "morph": "----GSM-"
      },
      {
        "form": "κόσμου.",
        "lemma": "κόσμος",
        "pos": "N-",
        "morph": "----GSM-"
      }
    ]
  },
  {
    "v": 3,
    "tokens": [
      {
        "form": "Καὶ",
        "lemma": "καί",
        "pos": "C-",
        "morph": "--------"
      },
      {
        "form": "ἐν",
        "lemma": "ἐν",
        "pos": "P-",
        "morph": "--------"
      },
      {
        "form": "τούτῳ",
        "lemma": "οὗτος",
        "pos": "RD",
        "morph": "----DSN-"
      },
      {
        "form": "γινώσκομεν",
        "lemma": "γινώσκω",
        "pos": "V-",
        "morph": "1PAI-P--"
      },
      {
        "form": "ὅτι",
        "lemma": "ὅτι",
        "pos": "C-",
        "morph": "--------"
      },
      {
        "form": "ἐγνώκαμεν",
        "lemma": "γινώσκω",
        "pos": "V-",
        "morph": "1XAI-P--"
      },
      {
        "form": "αὐτόν,",
        "lemma": "αὐτός",
        "pos": "RP",
        "morph": "----ASM-"
      },
      {
        "form": "ἐὰν",
        "lemma": "ἐάν",
        "pos": "C-",
        "morph": "--------"
      },
      {
        "form": "τὰς",
        "lemma": "ὁ",
        "pos": "RA",
        "morph": "----APF-"
      },
      {
        "form": "ἐντολὰς",
        "lemma": "ἐντολή",
        "pos": "N-",
        "morph": "----APF-"
      },
      {
        "form": "αὐτοῦ",
        "lemma": "αὐτός",
        "pos": "RP",
        "morph": "----GSM-"
      },
      {
        "form": "τηρῶμεν.",
        "lemma": "τηρέω",
        "pos": "V-",
        "morph": "1PAS-P--"
      }
    ]
  },
  {
    "v": 4,
    "tokens": [
      {
        "form": "ὁ",
        "lemma": "ὁ",
        "pos": "RA",
        "morph": "----NSM-"
      },
      {
        "form": "λέγων",
        "lemma": "λέγω",
        "pos": "V-",
        "morph": "-PAPNSM-"
      },
      {
        "form": "⸀ὅτι",
        "lemma": "ὅτι",
        "pos": "C-",
        "morph": "--------"
      },
      {
        "form": "Ἔγνωκα",
        "lemma": "γινώσκω",
        "pos": "V-",
        "morph": "1XAI-S--"
      },
      {
        "form": "αὐτὸν",
        "lemma": "αὐτός",
        "pos": "RP",
        "morph": "----ASM-"
      },
      {
        "form": "καὶ",
        "lemma": "καί",
        "pos": "C-",
        "morph": "--------"
      },
      {
        "form": "τὰς",
        "lemma": "ὁ",
        "pos": "RA",
        "morph": "----APF-"
      },
      {
        "form": "ἐντολὰς",
        "lemma": "ἐντολή",
        "pos": "N-",
        "morph": "----APF-"
      },
      {
        "form": "αὐτοῦ",
        "lemma": "αὐτός",
        "pos": "RP",
        "morph": "----GSM-"
      },
      {
        "form": "μὴ",
        "lemma": "μή",
        "pos": "D-",
        "morph": "--------"
      },
      {
        "form": "τηρῶν",
        "lemma": "τηρέω",
        "pos": "V-",
        "morph": "-PAPNSM-"
      },
      {
        "form": "ψεύστης",
        "lemma": "ψεύστης",
        "pos": "N-",
        "morph": "----NSM-"
      },
      {
        "form": "ἐστίν,",
        "lemma": "εἰμί",
        "pos": "V-",
        "morph": "3PAI-S--"
      },
      {
        "form": "καὶ",
        "lemma": "καί",
        "pos": "C-",
        "morph": "--------"
      },
      {
        "form": "ἐν",
        "lemma": "ἐν",
        "pos": "P-",
        "morph": "--------"
      },
      {
        "form": "τούτῳ",
        "lemma": "οὗτος",
        "pos": "RD",
        "morph": "----DSM-"
      },
      {
        "form": "ἡ",
        "lemma": "ὁ",
        "pos": "RA",
        "morph": "----NSF-"
      },
      {
        "form": "ἀλήθεια",
        "lemma": "ἀλήθεια",
        "pos": "N-",
        "morph": "----NSF-"
      },
      {
        "form": "οὐκ",
        "lemma": "οὐ",
        "pos": "D-",
        "morph": "--------"
      },
      {
        "form": "ἔστιν·",
        "lemma": "εἰμί",
        "pos": "V-",
        "morph": "3PAI-S--"
      }
    ]
  },
  {
    "v": 5,
    "tokens": [
      {
        "form": "ὃς",
        "lemma": "ὅς",
        "pos": "RR",
        "morph": "----NSM-"
      },
      {
        "form": "δ’",
        "lemma": "δέ",
        "pos": "C-",
        "morph": "--------"
      },
      {
        "form": "ἂν",
        "lemma": "ἄν",
        "pos": "X-",
        "morph": "--------"
      },
      {
        "form": "τηρῇ",
        "lemma": "τηρέω",
        "pos": "V-",
        "morph": "3PAS-S--"
      },
      {
        "form": "αὐτοῦ",
        "lemma": "αὐτός",
        "pos": "RP",
        "morph": "----GSM-"
      },
      {
        "form": "τὸν",
        "lemma": "ὁ",
        "pos": "RA",
        "morph": "----ASM-"
      },
      {
        "form": "λόγον,",
        "lemma": "λόγος",
        "pos": "N-",
        "morph": "----ASM-"
      },
      {
        "form": "ἀληθῶς",
        "lemma": "ἀληθῶς",
        "pos": "D-",
        "morph": "--------"
      },
      {
        "form": "ἐν",
        "lemma": "ἐν",
        "pos": "P-",
        "morph": "--------"
      },
      {
        "form": "τούτῳ",
        "lemma": "οὗτος",
        "pos": "RD",
        "morph": "----DSM-"
      },
      {
        "form": "ἡ",
        "lemma": "ὁ",
        "pos": "RA",
        "morph": "----NSF-"
      },
      {
        "form": "ἀγάπη",
        "lemma": "ἀγάπη",
        "pos": "N-",
        "morph": "----NSF-"
      },
      {
        "form": "τοῦ",
        "lemma": "ὁ",
        "pos": "RA",
        "morph": "----GSM-"
      },
      {
        "form": "θεοῦ",
        "lemma": "θεός",
        "pos": "N-",
        "morph": "----GSM-"
      },
      {
        "form": "τετελείωται.",
        "lemma": "τελειόω",
        "pos": "V-",
        "morph": "3XPI-S--"
      },
      {
        "form": "ἐν",
        "lemma": "ἐν",
        "pos": "P-",
        "morph": "--------"
      },
      {
        "form": "τούτῳ",
        "lemma": "οὗτος",
        "pos": "RD",
        "morph": "----DSN-"
      },
      {
        "form": "γινώσκομεν",
        "lemma": "γινώσκω",
        "pos": "V-",
        "morph": "1PAI-P--"
      },
      {
        "form": "ὅτι",
        "lemma": "ὅτι",
        "pos": "C-",
        "morph": "--------"
      },
      {
        "form": "ἐν",
        "lemma": "ἐν",
        "pos": "P-",
        "morph": "--------"
      },
      {
        "form": "αὐτῷ",
        "lemma": "αὐτός",
        "pos": "RP",
        "morph": "----DSM-"
      },
      {
        "form": "ἐσμεν·",
        "lemma": "εἰμί",
        "pos": "V-",
        "morph": "1PAI-P--"
      }
    ]
  },
  {
    "v": 6,
    "tokens": [
      {
        "form": "ὁ",
        "lemma": "ὁ",
        "pos": "RA",
        "morph": "----NSM-"
      },
      {
        "form": "λέγων",
        "lemma": "λέγω",
        "pos": "V-",
        "morph": "-PAPNSM-"
      },
      {
        "form": "ἐν",
        "lemma": "ἐν",
        "pos": "P-",
        "morph": "--------"
      },
      {
        "form": "αὐτῷ",
        "lemma": "αὐτός",
        "pos": "RP",
        "morph": "----DSM-"
      },
      {
        "form": "μένειν",
        "lemma": "μένω",
        "pos": "V-",
        "morph": "-PAN----"
      },
      {
        "form": "ὀφείλει",
        "lemma": "ὀφείλω",
        "pos": "V-",
        "morph": "3PAI-S--"
      },
      {
        "form": "καθὼς",
        "lemma": "καθώς",
        "pos": "C-",
        "morph": "--------"
      },
      {
        "form": "ἐκεῖνος",
        "lemma": "ἐκεῖνος",
        "pos": "RD",
        "morph": "----NSM-"
      },
      {
        "form": "περιεπάτησεν",
        "lemma": "περιπατέω",
        "pos": "V-",
        "morph": "3AAI-S--"
      },
      {
        "form": "καὶ",
        "lemma": "καί",
        "pos": "D-",
        "morph": "--------"
      },
      {
        "form": "⸀αὐτὸς",
        "lemma": "αὐτός",
        "pos": "RP",
        "morph": "----NSM-"
      },
      {
        "form": "περιπατεῖν.",
        "lemma": "περιπατέω",
        "pos": "V-",
        "morph": "-PAN----"
      }
    ]
  },
  {
    "v": 7,
    "tokens": [
      {
        "form": "⸀Ἀγαπητοί,",
        "lemma": "ἀγαπητός",
        "pos": "A-",
        "morph": "----VPM-"
      },
      {
        "form": "οὐκ",
        "lemma": "οὐ",
        "pos": "D-",
        "morph": "--------"
      },
      {
        "form": "ἐντολὴν",
        "lemma": "ἐντολή",
        "pos": "N-",
        "morph": "----ASF-"
      },
      {
        "form": "καινὴν",
        "lemma": "καινός",
        "pos": "A-",
        "morph": "----ASF-"
      },
      {
        "form": "γράφω",
        "lemma": "γράφω",
        "pos": "V-",
        "morph": "1PAI-S--"
      },
      {
        "form": "ὑμῖν,",
        "lemma": "σύ",
        "pos": "RP",
        "morph": "----DP--"
      },
      {
        "form": "ἀλλ’",
        "lemma": "ἀλλά",
        "pos": "C-",
        "morph": "--------"
      },
      {
        "form": "ἐντολὴν",
        "lemma": "ἐντολή",
        "pos": "N-",
        "morph": "----ASF-"
      },
      {
        "form": "παλαιὰν",
        "lemma": "παλαιός",
        "pos": "A-",
        "morph": "----ASF-"
      },
      {
        "form": "ἣν",
        "lemma": "ὅς",
        "pos": "RR",
        "morph": "----ASF-"
      },
      {
        "form": "εἴχετε",
        "lemma": "ἔχω",
        "pos": "V-",
        "morph": "2IAI-P--"
      },
      {
        "form": "ἀπ’",
        "lemma": "ἀπό",
        "pos": "P-",
        "morph": "--------"
      },
      {
        "form": "ἀρχῆς·",
        "lemma": "ἀρχή",
        "pos": "N-",
        "morph": "----GSF-"
      },
      {
        "form": "ἡ",
        "lemma": "ὁ",
        "pos": "RA",
        "morph": "----NSF-"
      },
      {
        "form": "ἐντολὴ",
        "lemma": "ἐντολή",
        "pos": "N-",
        "morph": "----NSF-"
      },
      {
        "form": "ἡ",
        "lemma": "ὁ",
        "pos": "RA",
        "morph": "----NSF-"
      },
      {
        "form": "παλαιά",
        "lemma": "παλαιός",
        "pos": "A-",
        "morph": "----NSF-"
      },
      {
        "form": "ἐστιν",
        "lemma": "εἰμί",
        "pos": "V-",
        "morph": "3PAI-S--"
      },
      {
        "form": "ὁ",
        "lemma": "ὁ",
        "pos": "RA",
        "morph": "----NSM-"
      },
      {
        "form": "λόγος",
        "lemma": "λόγος",
        "pos": "N-",
        "morph": "----NSM-"
      },
      {
        "form": "ὃν",
        "lemma": "ὅς",
        "pos": "RR",
        "morph": "----ASM-"
      },
      {
        "form": "⸀ἠκούσατε.",
        "lemma": "ἀκούω",
        "pos": "V-",
        "morph": "2AAI-P--"
      }
    ]
  },
  {
    "v": 8,
    "tokens": [
      {
        "form": "πάλιν",
        "lemma": "πάλιν",
        "pos": "D-",
        "morph": "--------"
      },
      {
        "form": "ἐντολὴν",
        "lemma": "ἐντολή",
        "pos": "N-",
        "morph": "----ASF-"
      },
      {
        "form": "καινὴν",
        "lemma": "καινός",
        "pos": "A-",
        "morph": "----ASF-"
      },
      {
        "form": "γράφω",
        "lemma": "γράφω",
        "pos": "V-",
        "morph": "1PAI-S--"
      },
      {
        "form": "ὑμῖν,",
        "lemma": "σύ",
        "pos": "RP",
        "morph": "----DP--"
      },
      {
        "form": "ὅ",
        "lemma": "ὅς",
        "pos": "RR",
        "morph": "----NSN-"
      },
      {
        "form": "ἐστιν",
        "lemma": "εἰμί",
        "pos": "V-",
        "morph": "3PAI-S--"
      },
      {
        "form": "ἀληθὲς",
        "lemma": "ἀληθής",
        "pos": "A-",
        "morph": "----NSN-"
      },
      {
        "form": "ἐν",
        "lemma": "ἐν",
        "pos": "P-",
        "morph": "--------"
      },
      {
        "form": "αὐτῷ",
        "lemma": "αὐτός",
        "pos": "RP",
        "morph": "----DSM-"
      },
      {
        "form": "καὶ",
        "lemma": "καί",
        "pos": "C-",
        "morph": "--------"
      },
      {
        "form": "ἐν",
        "lemma": "ἐν",
        "pos": "P-",
        "morph": "--------"
      },
      {
        "form": "ὑμῖν,",
        "lemma": "σύ",
        "pos": "RP",
        "morph": "----DP--"
      },
      {
        "form": "ὅτι",
        "lemma": "ὅτι",
        "pos": "C-",
        "morph": "--------"
      },
      {
        "form": "ἡ",
        "lemma": "ὁ",
        "pos": "RA",
        "morph": "----NSF-"
      },
      {
        "form": "σκοτία",
        "lemma": "σκοτία",
        "pos": "N-",
        "morph": "----NSF-"
      },
      {
        "form": "παράγεται",
        "lemma": "παράγω",
        "pos": "V-",
        "morph": "3PPI-S--"
      },
      {
        "form": "καὶ",
        "lemma": "καί",
        "pos": "C-",
        "morph": "--------"
      },
      {
        "form": "τὸ",
        "lemma": "ὁ",
        "pos": "RA",
        "morph": "----NSN-"
      },
      {
        "form": "φῶς",
        "lemma": "φῶς",
        "pos": "N-",
        "morph": "----NSN-"
      },
      {
        "form": "τὸ",
        "lemma": "ὁ",
        "pos": "RA",
        "morph": "----NSN-"
      },
      {
        "form": "ἀληθινὸν",
        "lemma": "ἀληθινός",
        "pos": "A-",
        "morph": "----NSN-"
      },
      {
        "form": "ἤδη",
        "lemma": "ἤδη",
        "pos": "D-",
        "morph": "--------"
      },
      {
        "form": "φαίνει.",
        "lemma": "φαίνω",
        "pos": "V-",
        "morph": "3PAI-S--"
      }
    ]
  },
  {
    "v": 9,
    "tokens": [
      {
        "form": "ὁ",
        "lemma": "ὁ",
        "pos": "RA",
        "morph": "----NSM-"
      },
      {
        "form": "λέγων",
        "lemma": "λέγω",
        "pos": "V-",
        "morph": "-PAPNSM-"
      },
      {
        "form": "ἐν",
        "lemma": "ἐν",
        "pos": "P-",
        "morph": "--------"
      },
      {
        "form": "τῷ",
        "lemma": "ὁ",
        "pos": "RA",
        "morph": "----DSN-"
      },
      {
        "form": "φωτὶ",
        "lemma": "φῶς",
        "pos": "N-",
        "morph": "----DSN-"
      },
      {
        "form": "εἶναι",
        "lemma": "εἰμί",
        "pos": "V-",
        "morph": "-PAN----"
      },
      {
        "form": "καὶ",
        "lemma": "καί",
        "pos": "C-",
        "morph": "--------"
      },
      {
        "form": "τὸν",
        "lemma": "ὁ",
        "pos": "RA",
        "morph": "----ASM-"
      },
      {
        "form": "ἀδελφὸν",
        "lemma": "ἀδελφός",
        "pos": "N-",
        "morph": "----ASM-"
      },
      {
        "form": "αὐτοῦ",
        "lemma": "αὐτός",
        "pos": "RP",
        "morph": "----GSM-"
      },
      {
        "form": "μισῶν",
        "lemma": "μισέω",
        "pos": "V-",
        "morph": "-PAPNSM-"
      },
      {
        "form": "ἐν",
        "lemma": "ἐν",
        "pos": "P-",
        "morph": "--------"
      },
      {
        "form": "τῇ",
        "lemma": "ὁ",
        "pos": "RA",
        "morph": "----DSF-"
      },
      {
        "form": "σκοτίᾳ",
        "lemma": "σκοτία",
        "pos": "N-",
        "morph": "----DSF-"
      },
      {
        "form": "ἐστὶν",
        "lemma": "εἰμί",
        "pos": "V-",
        "morph": "3PAI-S--"
      },
      {
        "form": "ἕως",
        "lemma": "ἕως",
        "pos": "P-",
        "morph": "--------"
      },
      {
        "form": "ἄρτι.",
        "lemma": "ἄρτι",
        "pos": "D-",
        "morph": "--------"
      }
    ]
  },
  {
    "v": 10,
    "tokens": [
      {
        "form": "ὁ",
        "lemma": "ὁ",
        "pos": "RA",
        "morph": "----NSM-"
      },
      {
        "form": "ἀγαπῶν",
        "lemma": "ἀγαπάω",
        "pos": "V-",
        "morph": "-PAPNSM-"
      },
      {
        "form": "τὸν",
        "lemma": "ὁ",
        "pos": "RA",
        "morph": "----ASM-"
      },
      {
        "form": "ἀδελφὸν",
        "lemma": "ἀδελφός",
        "pos": "N-",
        "morph": "----ASM-"
      },
      {
        "form": "αὐτοῦ",
        "lemma": "αὐτός",
        "pos": "RP",
        "morph": "----GSM-"
      },
      {
        "form": "ἐν",
        "lemma": "ἐν",
        "pos": "P-",
        "morph": "--------"
      },
      {
        "form": "τῷ",
        "lemma": "ὁ",
        "pos": "RA",
        "morph": "----DSN-"
      },
      {
        "form": "φωτὶ",
        "lemma": "φῶς",
        "pos": "N-",
        "morph": "----DSN-"
      },
      {
        "form": "μένει,",
        "lemma": "μένω",
        "pos": "V-",
        "morph": "3PAI-S--"
      },
      {
        "form": "καὶ",
        "lemma": "καί",
        "pos": "C-",
        "morph": "--------"
      },
      {
        "form": "σκάνδαλον",
        "lemma": "σκάνδαλον",
        "pos": "N-",
        "morph": "----NSN-"
      },
      {
        "form": "ἐν",
        "lemma": "ἐν",
        "pos": "P-",
        "morph": "--------"
      },
      {
        "form": "αὐτῷ",
        "lemma": "αὐτός",
        "pos": "RP",
        "morph": "----DSM-"
      },
      {
        "form": "οὐκ",
        "lemma": "οὐ",
        "pos": "D-",
        "morph": "--------"
      },
      {
        "form": "ἔστιν·",
        "lemma": "εἰμί",
        "pos": "V-",
        "morph": "3PAI-S--"
      }
    ]
  },
  {
    "v": 11,
    "tokens": [
      {
        "form": "ὁ",
        "lemma": "ὁ",
        "pos": "RA",
        "morph": "----NSM-"
      },
      {
        "form": "δὲ",
        "lemma": "δέ",
        "pos": "C-",
        "morph": "--------"
      },
      {
        "form": "μισῶν",
        "lemma": "μισέω",
        "pos": "V-",
        "morph": "-PAPNSM-"
      },
      {
        "form": "τὸν",
        "lemma": "ὁ",
        "pos": "RA",
        "morph": "----ASM-"
      },
      {
        "form": "ἀδελφὸν",
        "lemma": "ἀδελφός",
        "pos": "N-",
        "morph": "----ASM-"
      },
      {
        "form": "αὐτοῦ",
        "lemma": "αὐτός",
        "pos": "RP",
        "morph": "----GSM-"
      },
      {
        "form": "ἐν",
        "lemma": "ἐν",
        "pos": "P-",
        "morph": "--------"
      },
      {
        "form": "τῇ",
        "lemma": "ὁ",
        "pos": "RA",
        "morph": "----DSF-"
      },
      {
        "form": "σκοτίᾳ",
        "lemma": "σκοτία",
        "pos": "N-",
        "morph": "----DSF-"
      },
      {
        "form": "ἐστὶν",
        "lemma": "εἰμί",
        "pos": "V-",
        "morph": "3PAI-S--"
      },
      {
        "form": "καὶ",
        "lemma": "καί",
        "pos": "C-",
        "morph": "--------"
      },
      {
        "form": "ἐν",
        "lemma": "ἐν",
        "pos": "P-",
        "morph": "--------"
      },
      {
        "form": "τῇ",
        "lemma": "ὁ",
        "pos": "RA",
        "morph": "----DSF-"
      },
      {
        "form": "σκοτίᾳ",
        "lemma": "σκοτία",
        "pos": "N-",
        "morph": "----DSF-"
      },
      {
        "form": "περιπατεῖ,",
        "lemma": "περιπατέω",
        "pos": "V-",
        "morph": "3PAI-S--"
      },
      {
        "form": "καὶ",
        "lemma": "καί",
        "pos": "C-",
        "morph": "--------"
      },
      {
        "form": "οὐκ",
        "lemma": "οὐ",
        "pos": "D-",
        "morph": "--------"
      },
      {
        "form": "οἶδεν",
        "lemma": "οἶδα",
        "pos": "V-",
        "morph": "3XAI-S--"
      },
      {
        "form": "ποῦ",
        "lemma": "ποῦ",
        "pos": "D-",
        "morph": "--------"
      },
      {
        "form": "ὑπάγει,",
        "lemma": "ὑπάγω",
        "pos": "V-",
        "morph": "3PAI-S--"
      },
      {
        "form": "ὅτι",
        "lemma": "ὅτι",
        "pos": "C-",
        "morph": "--------"
      },
      {
        "form": "ἡ",
        "lemma": "ὁ",
        "pos": "RA",
        "morph": "----NSF-"
      },
      {
        "form": "σκοτία",
        "lemma": "σκοτία",
        "pos": "N-",
        "morph": "----NSF-"
      },
      {
        "form": "ἐτύφλωσεν",
        "lemma": "τυφλόω",
        "pos": "V-",
        "morph": "3AAI-S--"
      },
      {
        "form": "τοὺς",
        "lemma": "ὁ",
        "pos": "RA",
        "morph": "----APM-"
      },
      {
        "form": "ὀφθαλμοὺς",
        "lemma": "ὀφθαλμός",
        "pos": "N-",
        "morph": "----APM-"
      },
      {
        "form": "αὐτοῦ.",
        "lemma": "αὐτός",
        "pos": "RP",
        "morph": "----GSM-"
      }
    ]
  },
  {
    "v": 12,
    "tokens": [
      {
        "form": "Γράφω",
        "lemma": "γράφω",
        "pos": "V-",
        "morph": "1PAI-S--"
      },
      {
        "form": "ὑμῖν,",
        "lemma": "σύ",
        "pos": "RP",
        "morph": "----DP--"
      },
      {
        "form": "τεκνία,",
        "lemma": "τεκνίον",
        "pos": "N-",
        "morph": "----VPN-"
      },
      {
        "form": "ὅτι",
        "lemma": "ὅτι",
        "pos": "C-",
        "morph": "--------"
      },
      {
        "form": "ἀφέωνται",
        "lemma": "ἀφίημι",
        "pos": "V-",
        "morph": "3XPI-P--"
      },
      {
        "form": "ὑμῖν",
        "lemma": "σύ",
        "pos": "RP",
        "morph": "----DP--"
      },
      {
        "form": "αἱ",
        "lemma": "ὁ",
        "pos": "RA",
        "morph": "----NPF-"
      },
      {
        "form": "ἁμαρτίαι",
        "lemma": "ἁμαρτία",
        "pos": "N-",
        "morph": "----NPF-"
      },
      {
        "form": "διὰ",
        "lemma": "διά",
        "pos": "P-",
        "morph": "--------"
      },
      {
        "form": "τὸ",
        "lemma": "ὁ",
        "pos": "RA",
        "morph": "----ASN-"
      },
      {
        "form": "ὄνομα",
        "lemma": "ὄνομα",
        "pos": "N-",
        "morph": "----ASN-"
      },
      {
        "form": "αὐτοῦ·",
        "lemma": "αὐτός",
        "pos": "RP",
        "morph": "----GSM-"
      }
    ]
  },
  {
    "v": 13,
    "tokens": [
      {
        "form": "γράφω",
        "lemma": "γράφω",
        "pos": "V-",
        "morph": "1PAI-S--"
      },
      {
        "form": "ὑμῖν,",
        "lemma": "σύ",
        "pos": "RP",
        "morph": "----DP--"
      },
      {
        "form": "πατέρες,",
        "lemma": "πατήρ",
        "pos": "N-",
        "morph": "----VPM-"
      },
      {
        "form": "ὅτι",
        "lemma": "ὅτι",
        "pos": "C-",
        "morph": "--------"
      },
      {
        "form": "ἐγνώκατε",
        "lemma": "γινώσκω",
        "pos": "V-",
        "morph": "2XAI-P--"
      },
      {
        "form": "τὸν",
        "lemma": "ὁ",
        "pos": "RA",
        "morph": "----ASM-"
      },
      {
        "form": "ἀπ’",
        "lemma": "ἀπό",
        "pos": "P-",
        "morph": "--------"
      },
      {
        "form": "ἀρχῆς·",
        "lemma": "ἀρχή",
        "pos": "N-",
        "morph": "----GSF-"
      },
      {
        "form": "γράφω",
        "lemma": "γράφω",
        "pos": "V-",
        "morph": "1PAI-S--"
      },
      {
        "form": "ὑμῖν,",
        "lemma": "σύ",
        "pos": "RP",
        "morph": "----DP--"
      },
      {
        "form": "νεανίσκοι,",
        "lemma": "νεανίσκος",
        "pos": "N-",
        "morph": "----VPM-"
      },
      {
        "form": "ὅτι",
        "lemma": "ὅτι",
        "pos": "C-",
        "morph": "--------"
      },
      {
        "form": "νενικήκατε",
        "lemma": "νικάω",
        "pos": "V-",
        "morph": "2XAI-P--"
      },
      {
        "form": "τὸν",
        "lemma": "ὁ",
        "pos": "RA",
        "morph": "----ASM-"
      },
      {
        "form": "πονηρόν.",
        "lemma": "πονηρός",
        "pos": "A-",
        "morph": "----ASM-"
      }
    ]
  },
  {
    "v": 14,
    "tokens": [
      {
        "form": "⸀ἔγραψα",
        "lemma": "γράφω",
        "pos": "V-",
        "morph": "1AAI-S--"
      },
      {
        "form": "ὑμῖν,",
        "lemma": "σύ",
        "pos": "RP",
        "morph": "----DP--"
      },
      {
        "form": "παιδία,",
        "lemma": "παιδίον",
        "pos": "N-",
        "morph": "----VPN-"
      },
      {
        "form": "ὅτι",
        "lemma": "ὅτι",
        "pos": "C-",
        "morph": "--------"
      },
      {
        "form": "ἐγνώκατε",
        "lemma": "γινώσκω",
        "pos": "V-",
        "morph": "2XAI-P--"
      },
      {
        "form": "τὸν",
        "lemma": "ὁ",
        "pos": "RA",
        "morph": "----ASM-"
      },
      {
        "form": "πατέρα·",
        "lemma": "πατήρ",
        "pos": "N-",
        "morph": "----ASM-"
      },
      {
        "form": "ἔγραψα",
        "lemma": "γράφω",
        "pos": "V-",
        "morph": "1AAI-S--"
      },
      {
        "form": "ὑμῖν,",
        "lemma": "σύ",
        "pos": "RP",
        "morph": "----DP--"
      },
      {
        "form": "πατέρες,",
        "lemma": "πατήρ",
        "pos": "N-",
        "morph": "----VPM-"
      },
      {
        "form": "ὅτι",
        "lemma": "ὅτι",
        "pos": "C-",
        "morph": "--------"
      },
      {
        "form": "ἐγνώκατε",
        "lemma": "γινώσκω",
        "pos": "V-",
        "morph": "2XAI-P--"
      },
      {
        "form": "τὸν",
        "lemma": "ὁ",
        "pos": "RA",
        "morph": "----ASM-"
      },
      {
        "form": "ἀπ’",
        "lemma": "ἀπό",
        "pos": "P-",
        "morph": "--------"
      },
      {
        "form": "ἀρχῆς·",
        "lemma": "ἀρχή",
        "pos": "N-",
        "morph": "----GSF-"
      },
      {
        "form": "ἔγραψα",
        "lemma": "γράφω",
        "pos": "V-",
        "morph": "1AAI-S--"
      },
      {
        "form": "ὑμῖν,",
        "lemma": "σύ",
        "pos": "RP",
        "morph": "----DP--"
      },
      {
        "form": "νεανίσκοι,",
        "lemma": "νεανίσκος",
        "pos": "N-",
        "morph": "----VPM-"
      },
      {
        "form": "ὅτι",
        "lemma": "ὅτι",
        "pos": "C-",
        "morph": "--------"
      },
      {
        "form": "ἰσχυροί",
        "lemma": "ἰσχυρός",
        "pos": "A-",
        "morph": "----NPM-"
      },
      {
        "form": "ἐστε",
        "lemma": "εἰμί",
        "pos": "V-",
        "morph": "2PAI-P--"
      },
      {
        "form": "καὶ",
        "lemma": "καί",
        "pos": "C-",
        "morph": "--------"
      },
      {
        "form": "ὁ",
        "lemma": "ὁ",
        "pos": "RA",
        "morph": "----NSM-"
      },
      {
        "form": "λόγος",
        "lemma": "λόγος",
        "pos": "N-",
        "morph": "----NSM-"
      },
      {
        "form": "τοῦ",
        "lemma": "ὁ",
        "pos": "RA",
        "morph": "----GSM-"
      },
      {
        "form": "θεοῦ",
        "lemma": "θεός",
        "pos": "N-",
        "morph": "----GSM-"
      },
      {
        "form": "ἐν",
        "lemma": "ἐν",
        "pos": "P-",
        "morph": "--------"
      },
      {
        "form": "ὑμῖν",
        "lemma": "σύ",
        "pos": "RP",
        "morph": "----DP--"
      },
      {
        "form": "μένει",
        "lemma": "μένω",
        "pos": "V-",
        "morph": "3PAI-S--"
      },
      {
        "form": "καὶ",
        "lemma": "καί",
        "pos": "C-",
        "morph": "--------"
      },
      {
        "form": "νενικήκατε",
        "lemma": "νικάω",
        "pos": "V-",
        "morph": "2XAI-P--"
      },
      {
        "form": "τὸν",
        "lemma": "ὁ",
        "pos": "RA",
        "morph": "----ASM-"
      },
      {
        "form": "πονηρόν.",
        "lemma": "πονηρός",
        "pos": "A-",
        "morph": "----ASM-"
      }
    ]
  },
  {
    "v": 15,
    "tokens": [
      {
        "form": "Μὴ",
        "lemma": "μή",
        "pos": "D-",
        "morph": "--------"
      },
      {
        "form": "ἀγαπᾶτε",
        "lemma": "ἀγαπάω",
        "pos": "V-",
        "morph": "2PAD-P--"
      },
      {
        "form": "τὸν",
        "lemma": "ὁ",
        "pos": "RA",
        "morph": "----ASM-"
      },
      {
        "form": "κόσμον",
        "lemma": "κόσμος",
        "pos": "N-",
        "morph": "----ASM-"
      },
      {
        "form": "μηδὲ",
        "lemma": "μηδέ",
        "pos": "C-",
        "morph": "--------"
      },
      {
        "form": "τὰ",
        "lemma": "ὁ",
        "pos": "RA",
        "morph": "----APN-"
      },
      {
        "form": "ἐν",
        "lemma": "ἐν",
        "pos": "P-",
        "morph": "--------"
      },
      {
        "form": "τῷ",
        "lemma": "ὁ",
        "pos": "RA",
        "morph": "----DSM-"
      },
      {
        "form": "κόσμῳ.",
        "lemma": "κόσμος",
        "pos": "N-",
        "morph": "----DSM-"
      },
      {
        "form": "ἐάν",
        "lemma": "ἐάν",
        "pos": "C-",
        "morph": "--------"
      },
      {
        "form": "τις",
        "lemma": "τις",
        "pos": "RI",
        "morph": "----NSM-"
      },
      {
        "form": "ἀγαπᾷ",
        "lemma": "ἀγαπάω",
        "pos": "V-",
        "morph": "3PAS-S--"
      },
      {
        "form": "τὸν",
        "lemma": "ὁ",
        "pos": "RA",
        "morph": "----ASM-"
      },
      {
        "form": "κόσμον,",
        "lemma": "κόσμος",
        "pos": "N-",
        "morph": "----ASM-"
      },
      {
        "form": "οὐκ",
        "lemma": "οὐ",
        "pos": "D-",
        "morph": "--------"
      },
      {
        "form": "ἔστιν",
        "lemma": "εἰμί",
        "pos": "V-",
        "morph": "3PAI-S--"
      },
      {
        "form": "ἡ",
        "lemma": "ὁ",
        "pos": "RA",
        "morph": "----NSF-"
      },
      {
        "form": "ἀγάπη",
        "lemma": "ἀγάπη",
        "pos": "N-",
        "morph": "----NSF-"
      },
      {
        "form": "τοῦ",
        "lemma": "ὁ",
        "pos": "RA",
        "morph": "----GSM-"
      },
      {
        "form": "πατρὸς",
        "lemma": "πατήρ",
        "pos": "N-",
        "morph": "----GSM-"
      },
      {
        "form": "ἐν",
        "lemma": "ἐν",
        "pos": "P-",
        "morph": "--------"
      },
      {
        "form": "αὐτῷ·",
        "lemma": "αὐτός",
        "pos": "RP",
        "morph": "----DSM-"
      }
    ]
  },
  {
    "v": 16,
    "tokens": [
      {
        "form": "ὅτι",
        "lemma": "ὅτι",
        "pos": "C-",
        "morph": "--------"
      },
      {
        "form": "πᾶν",
        "lemma": "πᾶς",
        "pos": "A-",
        "morph": "----NSN-"
      },
      {
        "form": "τὸ",
        "lemma": "ὁ",
        "pos": "RA",
        "morph": "----NSN-"
      },
      {
        "form": "ἐν",
        "lemma": "ἐν",
        "pos": "P-",
        "morph": "--------"
      },
      {
        "form": "τῷ",
        "lemma": "ὁ",
        "pos": "RA",
        "morph": "----DSM-"
      },
      {
        "form": "κόσμῳ,",
        "lemma": "κόσμος",
        "pos": "N-",
        "morph": "----DSM-"
      },
      {
        "form": "ἡ",
        "lemma": "ὁ",
        "pos": "RA",
        "morph": "----NSF-"
      },
      {
        "form": "ἐπιθυμία",
        "lemma": "ἐπιθυμία",
        "pos": "N-",
        "morph": "----NSF-"
      },
      {
        "form": "τῆς",
        "lemma": "ὁ",
        "pos": "RA",
        "morph": "----GSF-"
      },
      {
        "form": "σαρκὸς",
        "lemma": "σάρξ",
        "pos": "N-",
        "morph": "----GSF-"
      },
      {
        "form": "καὶ",
        "lemma": "καί",
        "pos": "C-",
        "morph": "--------"
      },
      {
        "form": "ἡ",
        "lemma": "ὁ",
        "pos": "RA",
        "morph": "----NSF-"
      },
      {
        "form": "ἐπιθυμία",
        "lemma": "ἐπιθυμία",
        "pos": "N-",
        "morph": "----NSF-"
      },
      {
        "form": "τῶν",
        "lemma": "ὁ",
        "pos": "RA",
        "morph": "----GPM-"
      },
      {
        "form": "ὀφθαλμῶν",
        "lemma": "ὀφθαλμός",
        "pos": "N-",
        "morph": "----GPM-"
      },
      {
        "form": "καὶ",
        "lemma": "καί",
        "pos": "C-",
        "morph": "--------"
      },
      {
        "form": "ἡ",
        "lemma": "ὁ",
        "pos": "RA",
        "morph": "----NSF-"
      },
      {
        "form": "ἀλαζονεία",
        "lemma": "ἀλαζονεία",
        "pos": "N-",
        "morph": "----NSF-"
      },
      {
        "form": "τοῦ",
        "lemma": "ὁ",
        "pos": "RA",
        "morph": "----GSM-"
      },
      {
        "form": "βίου,",
        "lemma": "βίος",
        "pos": "N-",
        "morph": "----GSM-"
      },
      {
        "form": "οὐκ",
        "lemma": "οὐ",
        "pos": "D-",
        "morph": "--------"
      },
      {
        "form": "ἔστιν",
        "lemma": "εἰμί",
        "pos": "V-",
        "morph": "3PAI-S--"
      },
      {
        "form": "ἐκ",
        "lemma": "ἐκ",
        "pos": "P-",
        "morph": "--------"
      },
      {
        "form": "τοῦ",
        "lemma": "ὁ",
        "pos": "RA",
        "morph": "----GSM-"
      },
      {
        "form": "πατρός,",
        "lemma": "πατήρ",
        "pos": "N-",
        "morph": "----GSM-"
      },
      {
        "form": "ἀλλὰ",
        "lemma": "ἀλλά",
        "pos": "C-",
        "morph": "--------"
      },
      {
        "form": "ἐκ",
        "lemma": "ἐκ",
        "pos": "P-",
        "morph": "--------"
      },
      {
        "form": "τοῦ",
        "lemma": "ὁ",
        "pos": "RA",
        "morph": "----GSM-"
      },
      {
        "form": "κόσμου",
        "lemma": "κόσμος",
        "pos": "N-",
        "morph": "----GSM-"
      },
      {
        "form": "ἐστίν·",
        "lemma": "εἰμί",
        "pos": "V-",
        "morph": "3PAI-S--"
      }
    ]
  },
  {
    "v": 17,
    "tokens": [
      {
        "form": "καὶ",
        "lemma": "καί",
        "pos": "C-",
        "morph": "--------"
      },
      {
        "form": "ὁ",
        "lemma": "ὁ",
        "pos": "RA",
        "morph": "----NSM-"
      },
      {
        "form": "κόσμος",
        "lemma": "κόσμος",
        "pos": "N-",
        "morph": "----NSM-"
      },
      {
        "form": "παράγεται",
        "lemma": "παράγω",
        "pos": "V-",
        "morph": "3PPI-S--"
      },
      {
        "form": "καὶ",
        "lemma": "καί",
        "pos": "C-",
        "morph": "--------"
      },
      {
        "form": "ἡ",
        "lemma": "ὁ",
        "pos": "RA",
        "morph": "----NSF-"
      },
      {
        "form": "ἐπιθυμία",
        "lemma": "ἐπιθυμία",
        "pos": "N-",
        "morph": "----NSF-"
      },
      {
        "form": "αὐτοῦ,",
        "lemma": "αὐτός",
        "pos": "RP",
        "morph": "----GSM-"
      },
      {
        "form": "ὁ",
        "lemma": "ὁ",
        "pos": "RA",
        "morph": "----NSM-"
      },
      {
        "form": "δὲ",
        "lemma": "δέ",
        "pos": "C-",
        "morph": "--------"
      },
      {
        "form": "ποιῶν",
        "lemma": "ποιέω",
        "pos": "V-",
        "morph": "-PAPNSM-"
      },
      {
        "form": "τὸ",
        "lemma": "ὁ",
        "pos": "RA",
        "morph": "----ASN-"
      },
      {
        "form": "θέλημα",
        "lemma": "θέλημα",
        "pos": "N-",
        "morph": "----ASN-"
      },
      {
        "form": "τοῦ",
        "lemma": "ὁ",
        "pos": "RA",
        "morph": "----GSM-"
      },
      {
        "form": "θεοῦ",
        "lemma": "θεός",
        "pos": "N-",
        "morph": "----GSM-"
      },
      {
        "form": "μένει",
        "lemma": "μένω",
        "pos": "V-",
        "morph": "3PAI-S--"
      },
      {
        "form": "εἰς",
        "lemma": "εἰς",
        "pos": "P-",
        "morph": "--------"
      },
      {
        "form": "τὸν",
        "lemma": "ὁ",
        "pos": "RA",
        "morph": "----ASM-"
      },
      {
        "form": "αἰῶνα.",
        "lemma": "αἰών",
        "pos": "N-",
        "morph": "----ASM-"
      }
    ]
  },
  {
    "v": 18,
    "tokens": [
      {
        "form": "Παιδία,",
        "lemma": "παιδίον",
        "pos": "N-",
        "morph": "----VPN-"
      },
      {
        "form": "ἐσχάτη",
        "lemma": "ἔσχατος",
        "pos": "A-",
        "morph": "----NSF-"
      },
      {
        "form": "ὥρα",
        "lemma": "ὥρα",
        "pos": "N-",
        "morph": "----NSF-"
      },
      {
        "form": "ἐστίν,",
        "lemma": "εἰμί",
        "pos": "V-",
        "morph": "3PAI-S--"
      },
      {
        "form": "καὶ",
        "lemma": "καί",
        "pos": "C-",
        "morph": "--------"
      },
      {
        "form": "καθὼς",
        "lemma": "καθώς",
        "pos": "C-",
        "morph": "--------"
      },
      {
        "form": "ἠκούσατε",
        "lemma": "ἀκούω",
        "pos": "V-",
        "morph": "2AAI-P--"
      },
      {
        "form": "⸀ὅτι",
        "lemma": "ὅτι",
        "pos": "C-",
        "morph": "--------"
      },
      {
        "form": "ἀντίχριστος",
        "lemma": "ἀντίχριστος",
        "pos": "N-",
        "morph": "----NSM-"
      },
      {
        "form": "ἔρχεται,",
        "lemma": "ἔρχομαι",
        "pos": "V-",
        "morph": "3PMI-S--"
      },
      {
        "form": "καὶ",
        "lemma": "καί",
        "pos": "D-",
        "morph": "--------"
      },
      {
        "form": "νῦν",
        "lemma": "νῦν",
        "pos": "D-",
        "morph": "--------"
      },
      {
        "form": "ἀντίχριστοι",
        "lemma": "ἀντίχριστος",
        "pos": "N-",
        "morph": "----NPM-"
      },
      {
        "form": "πολλοὶ",
        "lemma": "πολύς",
        "pos": "A-",
        "morph": "----NPM-"
      },
      {
        "form": "γεγόνασιν·",
        "lemma": "γίνομαι",
        "pos": "V-",
        "morph": "3XAI-P--"
      },
      {
        "form": "ὅθεν",
        "lemma": "ὅθεν",
        "pos": "C-",
        "morph": "--------"
      },
      {
        "form": "γινώσκομεν",
        "lemma": "γινώσκω",
        "pos": "V-",
        "morph": "1PAI-P--"
      },
      {
        "form": "ὅτι",
        "lemma": "ὅτι",
        "pos": "C-",
        "morph": "--------"
      },
      {
        "form": "ἐσχάτη",
        "lemma": "ἔσχατος",
        "pos": "A-",
        "morph": "----NSF-"
      },
      {
        "form": "ὥρα",
        "lemma": "ὥρα",
        "pos": "N-",
        "morph": "----NSF-"
      },
      {
        "form": "ἐστίν.",
        "lemma": "εἰμί",
        "pos": "V-",
        "morph": "3PAI-S--"
      }
    ]
  },
  {
    "v": 19,
    "tokens": [
      {
        "form": "ἐξ",
        "lemma": "ἐκ",
        "pos": "P-",
        "morph": "--------"
      },
      {
        "form": "ἡμῶν",
        "lemma": "ἐγώ",
        "pos": "RP",
        "morph": "----GP--"
      },
      {
        "form": "ἐξῆλθαν,",
        "lemma": "ἐξέρχομαι",
        "pos": "V-",
        "morph": "3AAI-P--"
      },
      {
        "form": "ἀλλ’",
        "lemma": "ἀλλά",
        "pos": "C-",
        "morph": "--------"
      },
      {
        "form": "οὐκ",
        "lemma": "οὐ",
        "pos": "D-",
        "morph": "--------"
      },
      {
        "form": "ἦσαν",
        "lemma": "εἰμί",
        "pos": "V-",
        "morph": "3IAI-P--"
      },
      {
        "form": "ἐξ",
        "lemma": "ἐκ",
        "pos": "P-",
        "morph": "--------"
      },
      {
        "form": "ἡμῶν·",
        "lemma": "ἐγώ",
        "pos": "RP",
        "morph": "----GP--"
      },
      {
        "form": "εἰ",
        "lemma": "εἰ",
        "pos": "C-",
        "morph": "--------"
      },
      {
        "form": "γὰρ",
        "lemma": "γάρ",
        "pos": "C-",
        "morph": "--------"
      },
      {
        "form": "⸂ἐξ",
        "lemma": "ἐκ",
        "pos": "P-",
        "morph": "--------"
      },
      {
        "form": "ἡμῶν",
        "lemma": "ἐγώ",
        "pos": "RP",
        "morph": "----GP--"
      },
      {
        "form": "ἦσαν⸃,",
        "lemma": "εἰμί",
        "pos": "V-",
        "morph": "3IAI-P--"
      },
      {
        "form": "μεμενήκεισαν",
        "lemma": "μένω",
        "pos": "V-",
        "morph": "3YAI-P--"
      },
      {
        "form": "ἂν",
        "lemma": "ἄν",
        "pos": "X-",
        "morph": "--------"
      },
      {
        "form": "μεθ’",
        "lemma": "μετά",
        "pos": "P-",
        "morph": "--------"
      },
      {
        "form": "ἡμῶν·",
        "lemma": "ἐγώ",
        "pos": "RP",
        "morph": "----GP--"
      },
      {
        "form": "ἀλλ’",
        "lemma": "ἀλλά",
        "pos": "C-",
        "morph": "--------"
      },
      {
        "form": "ἵνα",
        "lemma": "ἵνα",
        "pos": "C-",
        "morph": "--------"
      },
      {
        "form": "φανερωθῶσιν",
        "lemma": "φανερόω",
        "pos": "V-",
        "morph": "3APS-P--"
      },
      {
        "form": "ὅτι",
        "lemma": "ὅτι",
        "pos": "C-",
        "morph": "--------"
      },
      {
        "form": "οὐκ",
        "lemma": "οὐ",
        "pos": "D-",
        "morph": "--------"
      },
      {
        "form": "εἰσὶν",
        "lemma": "εἰμί",
        "pos": "V-",
        "morph": "3PAI-P--"
      },
      {
        "form": "πάντες",
        "lemma": "πᾶς",
        "pos": "A-",
        "morph": "----NPM-"
      },
      {
        "form": "ἐξ",
        "lemma": "ἐκ",
        "pos": "P-",
        "morph": "--------"
      },
      {
        "form": "ἡμῶν.",
        "lemma": "ἐγώ",
        "pos": "RP",
        "morph": "----GP--"
      }
    ]
  },
  {
    "v": 20,
    "tokens": [
      {
        "form": "καὶ",
        "lemma": "καί",
        "pos": "C-",
        "morph": "--------"
      },
      {
        "form": "ὑμεῖς",
        "lemma": "σύ",
        "pos": "RP",
        "morph": "----NP--"
      },
      {
        "form": "χρῖσμα",
        "lemma": "χρῖσμα",
        "pos": "N-",
        "morph": "----ASN-"
      },
      {
        "form": "ἔχετε",
        "lemma": "ἔχω",
        "pos": "V-",
        "morph": "2PAI-P--"
      },
      {
        "form": "ἀπὸ",
        "lemma": "ἀπό",
        "pos": "P-",
        "morph": "--------"
      },
      {
        "form": "τοῦ",
        "lemma": "ὁ",
        "pos": "RA",
        "morph": "----GSM-"
      },
      {
        "form": "ἁγίου",
        "lemma": "ἅγιος",
        "pos": "A-",
        "morph": "----GSM-"
      },
      {
        "form": "⸀καὶ",
        "lemma": "καί",
        "pos": "C-",
        "morph": "--------"
      },
      {
        "form": "οἴδατε",
        "lemma": "οἶδα",
        "pos": "V-",
        "morph": "2XAI-P--"
      },
      {
        "form": "⸀πάντες·",
        "lemma": "πᾶς",
        "pos": "A-",
        "morph": "----NPM-"
      }
    ]
  },
  {
    "v": 21,
    "tokens": [
      {
        "form": "οὐκ",
        "lemma": "οὐ",
        "pos": "D-",
        "morph": "--------"
      },
      {
        "form": "ἔγραψα",
        "lemma": "γράφω",
        "pos": "V-",
        "morph": "1AAI-S--"
      },
      {
        "form": "ὑμῖν",
        "lemma": "σύ",
        "pos": "RP",
        "morph": "----DP--"
      },
      {
        "form": "ὅτι",
        "lemma": "ὅτι",
        "pos": "C-",
        "morph": "--------"
      },
      {
        "form": "οὐκ",
        "lemma": "οὐ",
        "pos": "D-",
        "morph": "--------"
      },
      {
        "form": "οἴδατε",
        "lemma": "οἶδα",
        "pos": "V-",
        "morph": "2XAI-P--"
      },
      {
        "form": "τὴν",
        "lemma": "ὁ",
        "pos": "RA",
        "morph": "----ASF-"
      },
      {
        "form": "ἀλήθειαν,",
        "lemma": "ἀλήθεια",
        "pos": "N-",
        "morph": "----ASF-"
      },
      {
        "form": "ἀλλ’",
        "lemma": "ἀλλά",
        "pos": "C-",
        "morph": "--------"
      },
      {
        "form": "ὅτι",
        "lemma": "ὅτι",
        "pos": "C-",
        "morph": "--------"
      },
      {
        "form": "οἴδατε",
        "lemma": "οἶδα",
        "pos": "V-",
        "morph": "2XAI-P--"
      },
      {
        "form": "αὐτήν,",
        "lemma": "αὐτός",
        "pos": "RP",
        "morph": "----ASF-"
      },
      {
        "form": "καὶ",
        "lemma": "καί",
        "pos": "C-",
        "morph": "--------"
      },
      {
        "form": "ὅτι",
        "lemma": "ὅτι",
        "pos": "C-",
        "morph": "--------"
      },
      {
        "form": "πᾶν",
        "lemma": "πᾶς",
        "pos": "A-",
        "morph": "----NSN-"
      },
      {
        "form": "ψεῦδος",
        "lemma": "ψεῦδος",
        "pos": "N-",
        "morph": "----NSN-"
      },
      {
        "form": "ἐκ",
        "lemma": "ἐκ",
        "pos": "P-",
        "morph": "--------"
      },
      {
        "form": "τῆς",
        "lemma": "ὁ",
        "pos": "RA",
        "morph": "----GSF-"
      },
      {
        "form": "ἀληθείας",
        "lemma": "ἀλήθεια",
        "pos": "N-",
        "morph": "----GSF-"
      },
      {
        "form": "οὐκ",
        "lemma": "οὐ",
        "pos": "D-",
        "morph": "--------"
      },
      {
        "form": "ἔστιν.",
        "lemma": "εἰμί",
        "pos": "V-",
        "morph": "3PAI-S--"
      }
    ]
  },
  {
    "v": 22,
    "tokens": [
      {
        "form": "τίς",
        "lemma": "τίς",
        "pos": "RI",
        "morph": "----NSM-"
      },
      {
        "form": "ἐστιν",
        "lemma": "εἰμί",
        "pos": "V-",
        "morph": "3PAI-S--"
      },
      {
        "form": "ὁ",
        "lemma": "ὁ",
        "pos": "RA",
        "morph": "----NSM-"
      },
      {
        "form": "ψεύστης",
        "lemma": "ψεύστης",
        "pos": "N-",
        "morph": "----NSM-"
      },
      {
        "form": "εἰ",
        "lemma": "εἰ",
        "pos": "C-",
        "morph": "--------"
      },
      {
        "form": "μὴ",
        "lemma": "μή",
        "pos": "D-",
        "morph": "--------"
      },
      {
        "form": "ὁ",
        "lemma": "ὁ",
        "pos": "RA",
        "morph": "----NSM-"
      },
      {
        "form": "ἀρνούμενος",
        "lemma": "ἀρνέομαι",
        "pos": "V-",
        "morph": "-PMPNSM-"
      },
      {
        "form": "ὅτι",
        "lemma": "ὅτι",
        "pos": "C-",
        "morph": "--------"
      },
      {
        "form": "Ἰησοῦς",
        "lemma": "Ἰησοῦς",
        "pos": "N-",
        "morph": "----NSM-"
      },
      {
        "form": "οὐκ",
        "lemma": "οὐ",
        "pos": "D-",
        "morph": "--------"
      },
      {
        "form": "ἔστιν",
        "lemma": "εἰμί",
        "pos": "V-",
        "morph": "3PAI-S--"
      },
      {
        "form": "ὁ",
        "lemma": "ὁ",
        "pos": "RA",
        "morph": "----NSM-"
      },
      {
        "form": "χριστός;",
        "lemma": "Χριστός",
        "pos": "N-",
        "morph": "----NSM-"
      },
      {
        "form": "οὗτός",
        "lemma": "οὗτος",
        "pos": "RD",
        "morph": "----NSM-"
      },
      {
        "form": "ἐστιν",
        "lemma": "εἰμί",
        "pos": "V-",
        "morph": "3PAI-S--"
      },
      {
        "form": "ὁ",
        "lemma": "ὁ",
        "pos": "RA",
        "morph": "----NSM-"
      },
      {
        "form": "ἀντίχριστος,",
        "lemma": "ἀντίχριστος",
        "pos": "N-",
        "morph": "----NSM-"
      },
      {
        "form": "ὁ",
        "lemma": "ὁ",
        "pos": "RA",
        "morph": "----NSM-"
      },
      {
        "form": "ἀρνούμενος",
        "lemma": "ἀρνέομαι",
        "pos": "V-",
        "morph": "-PMPNSM-"
      },
      {
        "form": "τὸν",
        "lemma": "ὁ",
        "pos": "RA",
        "morph": "----ASM-"
      },
      {
        "form": "πατέρα",
        "lemma": "πατήρ",
        "pos": "N-",
        "morph": "----ASM-"
      },
      {
        "form": "καὶ",
        "lemma": "καί",
        "pos": "C-",
        "morph": "--------"
      },
      {
        "form": "τὸν",
        "lemma": "ὁ",
        "pos": "RA",
        "morph": "----ASM-"
      },
      {
        "form": "υἱόν.",
        "lemma": "υἱός",
        "pos": "N-",
        "morph": "----ASM-"
      }
    ]
  },
  {
    "v": 23,
    "tokens": [
      {
        "form": "πᾶς",
        "lemma": "πᾶς",
        "pos": "A-",
        "morph": "----NSM-"
      },
      {
        "form": "ὁ",
        "lemma": "ὁ",
        "pos": "RA",
        "morph": "----NSM-"
      },
      {
        "form": "ἀρνούμενος",
        "lemma": "ἀρνέομαι",
        "pos": "V-",
        "morph": "-PMPNSM-"
      },
      {
        "form": "τὸν",
        "lemma": "ὁ",
        "pos": "RA",
        "morph": "----ASM-"
      },
      {
        "form": "υἱὸν",
        "lemma": "υἱός",
        "pos": "N-",
        "morph": "----ASM-"
      },
      {
        "form": "οὐδὲ",
        "lemma": "οὐδέ",
        "pos": "D-",
        "morph": "--------"
      },
      {
        "form": "τὸν",
        "lemma": "ὁ",
        "pos": "RA",
        "morph": "----ASM-"
      },
      {
        "form": "πατέρα",
        "lemma": "πατήρ",
        "pos": "N-",
        "morph": "----ASM-"
      },
      {
        "form": "ἔχει·",
        "lemma": "ἔχω",
        "pos": "V-",
        "morph": "3PAI-S--"
      },
      {
        "form": "⸂ὁ",
        "lemma": "ὁ",
        "pos": "RA",
        "morph": "----NSM-"
      },
      {
        "form": "ὁμολογῶν",
        "lemma": "ὁμολογέω",
        "pos": "V-",
        "morph": "-PAPNSM-"
      },
      {
        "form": "τὸν",
        "lemma": "ὁ",
        "pos": "RA",
        "morph": "----ASM-"
      },
      {
        "form": "υἱὸν",
        "lemma": "υἱός",
        "pos": "N-",
        "morph": "----ASM-"
      },
      {
        "form": "καὶ",
        "lemma": "καί",
        "pos": "D-",
        "morph": "--------"
      },
      {
        "form": "τὸν",
        "lemma": "ὁ",
        "pos": "RA",
        "morph": "----ASM-"
      },
      {
        "form": "πατέρα",
        "lemma": "πατήρ",
        "pos": "N-",
        "morph": "----ASM-"
      },
      {
        "form": "ἔχει⸃.",
        "lemma": "ἔχω",
        "pos": "V-",
        "morph": "3PAI-S--"
      }
    ]
  },
  {
    "v": 24,
    "tokens": [
      {
        "form": "⸀ὑμεῖς",
        "lemma": "σύ",
        "pos": "RP",
        "morph": "----NP--"
      },
      {
        "form": "ὃ",
        "lemma": "ὅς",
        "pos": "RR",
        "morph": "----ASN-"
      },
      {
        "form": "ἠκούσατε",
        "lemma": "ἀκούω",
        "pos": "V-",
        "morph": "2AAI-P--"
      },
      {
        "form": "ἀπ’",
        "lemma": "ἀπό",
        "pos": "P-",
        "morph": "--------"
      },
      {
        "form": "ἀρχῆς,",
        "lemma": "ἀρχή",
        "pos": "N-",
        "morph": "----GSF-"
      },
      {
        "form": "ἐν",
        "lemma": "ἐν",
        "pos": "P-",
        "morph": "--------"
      },
      {
        "form": "ὑμῖν",
        "lemma": "σύ",
        "pos": "RP",
        "morph": "----DP--"
      },
      {
        "form": "μενέτω·",
        "lemma": "μένω",
        "pos": "V-",
        "morph": "3PAD-S--"
      },
      {
        "form": "ἐὰν",
        "lemma": "ἐάν",
        "pos": "C-",
        "morph": "--------"
      },
      {
        "form": "ἐν",
        "lemma": "ἐν",
        "pos": "P-",
        "morph": "--------"
      },
      {
        "form": "ὑμῖν",
        "lemma": "σύ",
        "pos": "RP",
        "morph": "----DP--"
      },
      {
        "form": "μείνῃ",
        "lemma": "μένω",
        "pos": "V-",
        "morph": "3AAS-S--"
      },
      {
        "form": "ὃ",
        "lemma": "ὅς",
        "pos": "RR",
        "morph": "----ASN-"
      },
      {
        "form": "ἀπ’",
        "lemma": "ἀπό",
        "pos": "P-",
        "morph": "--------"
      },
      {
        "form": "ἀρχῆς",
        "lemma": "ἀρχή",
        "pos": "N-",
        "morph": "----GSF-"
      },
      {
        "form": "ἠκούσατε,",
        "lemma": "ἀκούω",
        "pos": "V-",
        "morph": "2AAI-P--"
      },
      {
        "form": "καὶ",
        "lemma": "καί",
        "pos": "D-",
        "morph": "--------"
      },
      {
        "form": "ὑμεῖς",
        "lemma": "σύ",
        "pos": "RP",
        "morph": "----NP--"
      },
      {
        "form": "ἐν",
        "lemma": "ἐν",
        "pos": "P-",
        "morph": "--------"
      },
      {
        "form": "τῷ",
        "lemma": "ὁ",
        "pos": "RA",
        "morph": "----DSM-"
      },
      {
        "form": "υἱῷ",
        "lemma": "υἱός",
        "pos": "N-",
        "morph": "----DSM-"
      },
      {
        "form": "καὶ",
        "lemma": "καί",
        "pos": "C-",
        "morph": "--------"
      },
      {
        "form": "ἐν",
        "lemma": "ἐν",
        "pos": "P-",
        "morph": "--------"
      },
      {
        "form": "τῷ",
        "lemma": "ὁ",
        "pos": "RA",
        "morph": "----DSM-"
      },
      {
        "form": "πατρὶ",
        "lemma": "πατήρ",
        "pos": "N-",
        "morph": "----DSM-"
      },
      {
        "form": "μενεῖτε.",
        "lemma": "μένω",
        "pos": "V-",
        "morph": "2FAI-P--"
      }
    ]
  },
  {
    "v": 25,
    "tokens": [
      {
        "form": "καὶ",
        "lemma": "καί",
        "pos": "C-",
        "morph": "--------"
      },
      {
        "form": "αὕτη",
        "lemma": "οὗτος",
        "pos": "RD",
        "morph": "----NSF-"
      },
      {
        "form": "ἐστὶν",
        "lemma": "εἰμί",
        "pos": "V-",
        "morph": "3PAI-S--"
      },
      {
        "form": "ἡ",
        "lemma": "ὁ",
        "pos": "RA",
        "morph": "----NSF-"
      },
      {
        "form": "ἐπαγγελία",
        "lemma": "ἐπαγγελία",
        "pos": "N-",
        "morph": "----NSF-"
      },
      {
        "form": "ἣν",
        "lemma": "ὅς",
        "pos": "RR",
        "morph": "----ASF-"
      },
      {
        "form": "αὐτὸς",
        "lemma": "αὐτός",
        "pos": "RP",
        "morph": "----NSM-"
      },
      {
        "form": "ἐπηγγείλατο",
        "lemma": "ἐπαγγέλλομαι",
        "pos": "V-",
        "morph": "3AMI-S--"
      },
      {
        "form": "ἡμῖν,",
        "lemma": "ἐγώ",
        "pos": "RP",
        "morph": "----DP--"
      },
      {
        "form": "τὴν",
        "lemma": "ὁ",
        "pos": "RA",
        "morph": "----ASF-"
      },
      {
        "form": "ζωὴν",
        "lemma": "ζωή",
        "pos": "N-",
        "morph": "----ASF-"
      },
      {
        "form": "τὴν",
        "lemma": "ὁ",
        "pos": "RA",
        "morph": "----ASF-"
      },
      {
        "form": "αἰώνιον.",
        "lemma": "αἰώνιος",
        "pos": "A-",
        "morph": "----ASF-"
      }
    ]
  },
  {
    "v": 26,
    "tokens": [
      {
        "form": "Ταῦτα",
        "lemma": "οὗτος",
        "pos": "RD",
        "morph": "----APN-"
      },
      {
        "form": "ἔγραψα",
        "lemma": "γράφω",
        "pos": "V-",
        "morph": "1AAI-S--"
      },
      {
        "form": "ὑμῖν",
        "lemma": "σύ",
        "pos": "RP",
        "morph": "----DP--"
      },
      {
        "form": "περὶ",
        "lemma": "περί",
        "pos": "P-",
        "morph": "--------"
      },
      {
        "form": "τῶν",
        "lemma": "ὁ",
        "pos": "RA",
        "morph": "----GPM-"
      },
      {
        "form": "πλανώντων",
        "lemma": "πλανάω",
        "pos": "V-",
        "morph": "-PAPGPM-"
      },
      {
        "form": "ὑμᾶς.",
        "lemma": "σύ",
        "pos": "RP",
        "morph": "----AP--"
      }
    ]
  },
  {
    "v": 27,
    "tokens": [
      {
        "form": "καὶ",
        "lemma": "καί",
        "pos": "C-",
        "morph": "--------"
      },
      {
        "form": "ὑμεῖς",
        "lemma": "σύ",
        "pos": "RP",
        "morph": "----NP--"
      },
      {
        "form": "τὸ",
        "lemma": "ὁ",
        "pos": "RA",
        "morph": "----NSN-"
      },
      {
        "form": "χρῖσμα",
        "lemma": "χρῖσμα",
        "pos": "N-",
        "morph": "----NSN-"
      },
      {
        "form": "ὃ",
        "lemma": "ὅς",
        "pos": "RR",
        "morph": "----ASN-"
      },
      {
        "form": "ἐλάβετε",
        "lemma": "λαμβάνω",
        "pos": "V-",
        "morph": "2AAI-P--"
      },
      {
        "form": "ἀπ’",
        "lemma": "ἀπό",
        "pos": "P-",
        "morph": "--------"
      },
      {
        "form": "αὐτοῦ",
        "lemma": "αὐτός",
        "pos": "RP",
        "morph": "----GSM-"
      },
      {
        "form": "⸂μένει",
        "lemma": "μένω",
        "pos": "V-",
        "morph": "3PAI-S--"
      },
      {
        "form": "ἐν",
        "lemma": "ἐν",
        "pos": "P-",
        "morph": "--------"
      },
      {
        "form": "ὑμῖν⸃,",
        "lemma": "σύ",
        "pos": "RP",
        "morph": "----DP--"
      },
      {
        "form": "καὶ",
        "lemma": "καί",
        "pos": "C-",
        "morph": "--------"
      },
      {
        "form": "οὐ",
        "lemma": "οὐ",
        "pos": "D-",
        "morph": "--------"
      },
      {
        "form": "χρείαν",
        "lemma": "χρεία",
        "pos": "N-",
        "morph": "----ASF-"
      },
      {
        "form": "ἔχετε",
        "lemma": "ἔχω",
        "pos": "V-",
        "morph": "2PAI-P--"
      },
      {
        "form": "ἵνα",
        "lemma": "ἵνα",
        "pos": "C-",
        "morph": "--------"
      },
      {
        "form": "τις",
        "lemma": "τις",
        "pos": "RI",
        "morph": "----NSM-"
      },
      {
        "form": "διδάσκῃ",
        "lemma": "διδάσκω",
        "pos": "V-",
        "morph": "3PAS-S--"
      },
      {
        "form": "ὑμᾶς·",
        "lemma": "σύ",
        "pos": "RP",
        "morph": "----AP--"
      },
      {
        "form": "ἀλλ’",
        "lemma": "ἀλλά",
        "pos": "C-",
        "morph": "--------"
      },
      {
        "form": "ὡς",
        "lemma": "ὡς",
        "pos": "C-",
        "morph": "--------"
      },
      {
        "form": "τὸ",
        "lemma": "ὁ",
        "pos": "RA",
        "morph": "----NSN-"
      },
      {
        "form": "⸀αὐτοῦ",
        "lemma": "αὐτός",
        "pos": "RP",
        "morph": "----GSM-"
      },
      {
        "form": "χρῖσμα",
        "lemma": "χρῖσμα",
        "pos": "N-",
        "morph": "----NSN-"
      },
      {
        "form": "διδάσκει",
        "lemma": "διδάσκω",
        "pos": "V-",
        "morph": "3PAI-S--"
      },
      {
        "form": "ὑμᾶς",
        "lemma": "σύ",
        "pos": "RP",
        "morph": "----AP--"
      },
      {
        "form": "περὶ",
        "lemma": "περί",
        "pos": "P-",
        "morph": "--------"
      },
      {
        "form": "πάντων,",
        "lemma": "πᾶς",
        "pos": "A-",
        "morph": "----GPN-"
      },
      {
        "form": "καὶ",
        "lemma": "καί",
        "pos": "C-",
        "morph": "--------"
      },
      {
        "form": "ἀληθές",
        "lemma": "ἀληθής",
        "pos": "A-",
        "morph": "----NSN-"
      },
      {
        "form": "ἐστιν",
        "lemma": "εἰμί",
        "pos": "V-",
        "morph": "3PAI-S--"
      },
      {
        "form": "καὶ",
        "lemma": "καί",
        "pos": "C-",
        "morph": "--------"
      },
      {
        "form": "οὐκ",
        "lemma": "οὐ",
        "pos": "D-",
        "morph": "--------"
      },
      {
        "form": "ἔστιν",
        "lemma": "εἰμί",
        "pos": "V-",
        "morph": "3PAI-S--"
      },
      {
        "form": "ψεῦδος,",
        "lemma": "ψεῦδος",
        "pos": "N-",
        "morph": "----NSN-"
      },
      {
        "form": "καὶ",
        "lemma": "καί",
        "pos": "C-",
        "morph": "--------"
      },
      {
        "form": "καθὼς",
        "lemma": "καθώς",
        "pos": "C-",
        "morph": "--------"
      },
      {
        "form": "ἐδίδαξεν",
        "lemma": "διδάσκω",
        "pos": "V-",
        "morph": "3AAI-S--"
      },
      {
        "form": "ὑμᾶς,",
        "lemma": "σύ",
        "pos": "RP",
        "morph": "----AP--"
      },
      {
        "form": "⸀μένετε",
        "lemma": "μένω",
        "pos": "V-",
        "morph": "2PAI-P--"
      },
      {
        "form": "ἐν",
        "lemma": "ἐν",
        "pos": "P-",
        "morph": "--------"
      },
      {
        "form": "αὐτῷ.",
        "lemma": "αὐτός",
        "pos": "RP",
        "morph": "----DSM-"
      }
    ]
  },
  {
    "v": 28,
    "tokens": [
      {
        "form": "Καὶ",
        "lemma": "καί",
        "pos": "C-",
        "morph": "--------"
      },
      {
        "form": "νῦν,",
        "lemma": "νῦν",
        "pos": "D-",
        "morph": "--------"
      },
      {
        "form": "τεκνία,",
        "lemma": "τεκνίον",
        "pos": "N-",
        "morph": "----VPN-"
      },
      {
        "form": "μένετε",
        "lemma": "μένω",
        "pos": "V-",
        "morph": "2PAD-P--"
      },
      {
        "form": "ἐν",
        "lemma": "ἐν",
        "pos": "P-",
        "morph": "--------"
      },
      {
        "form": "αὐτῷ,",
        "lemma": "αὐτός",
        "pos": "RP",
        "morph": "----DSM-"
      },
      {
        "form": "ἵνα",
        "lemma": "ἵνα",
        "pos": "C-",
        "morph": "--------"
      },
      {
        "form": "⸀ἐὰν",
        "lemma": "ἐάν",
        "pos": "C-",
        "morph": "--------"
      },
      {
        "form": "φανερωθῇ",
        "lemma": "φανερόω",
        "pos": "V-",
        "morph": "3APS-S--"
      },
      {
        "form": "⸀σχῶμεν",
        "lemma": "ἔχω",
        "pos": "V-",
        "morph": "1AAS-P--"
      },
      {
        "form": "παρρησίαν",
        "lemma": "παρρησία",
        "pos": "N-",
        "morph": "----ASF-"
      },
      {
        "form": "καὶ",
        "lemma": "καί",
        "pos": "C-",
        "morph": "--------"
      },
      {
        "form": "μὴ",
        "lemma": "μή",
        "pos": "D-",
        "morph": "--------"
      },
      {
        "form": "αἰσχυνθῶμεν",
        "lemma": "αἰσχύνομαι",
        "pos": "V-",
        "morph": "1APS-P--"
      },
      {
        "form": "ἀπ’",
        "lemma": "ἀπό",
        "pos": "P-",
        "morph": "--------"
      },
      {
        "form": "αὐτοῦ",
        "lemma": "αὐτός",
        "pos": "RP",
        "morph": "----GSM-"
      },
      {
        "form": "ἐν",
        "lemma": "ἐν",
        "pos": "P-",
        "morph": "--------"
      },
      {
        "form": "τῇ",
        "lemma": "ὁ",
        "pos": "RA",
        "morph": "----DSF-"
      },
      {
        "form": "παρουσίᾳ",
        "lemma": "παρουσία",
        "pos": "N-",
        "morph": "----DSF-"
      },
      {
        "form": "αὐτοῦ.",
        "lemma": "αὐτός",
        "pos": "RP",
        "morph": "----GSM-"
      }
    ]
  },
  {
    "v": 29,
    "tokens": [
      {
        "form": "ἐὰν",
        "lemma": "ἐάν",
        "pos": "C-",
        "morph": "--------"
      },
      {
        "form": "εἰδῆτε",
        "lemma": "οἶδα",
        "pos": "V-",
        "morph": "2XAS-P--"
      },
      {
        "form": "ὅτι",
        "lemma": "ὅτι",
        "pos": "C-",
        "morph": "--------"
      },
      {
        "form": "δίκαιός",
        "lemma": "δίκαιος",
        "pos": "A-",
        "morph": "----NSM-"
      },
      {
        "form": "ἐστιν,",
        "lemma": "εἰμί",
        "pos": "V-",
        "morph": "3PAI-S--"
      },
      {
        "form": "γινώσκετε",
        "lemma": "γινώσκω",
        "pos": "V-",
        "morph": "2PAI-P--"
      },
      {
        "form": "⸀ὅτι",
        "lemma": "ὅτι",
        "pos": "C-",
        "morph": "--------"
      },
      {
        "form": "πᾶς",
        "lemma": "πᾶς",
        "pos": "A-",
        "morph": "----NSM-"
      },
      {
        "form": "ὁ",
        "lemma": "ὁ",
        "pos": "RA",
        "morph": "----NSM-"
      },
      {
        "form": "ποιῶν",
        "lemma": "ποιέω",
        "pos": "V-",
        "morph": "-PAPNSM-"
      },
      {
        "form": "τὴν",
        "lemma": "ὁ",
        "pos": "RA",
        "morph": "----ASF-"
      },
      {
        "form": "δικαιοσύνην",
        "lemma": "δικαιοσύνη",
        "pos": "N-",
        "morph": "----ASF-"
      },
      {
        "form": "ἐξ",
        "lemma": "ἐκ",
        "pos": "P-",
        "morph": "--------"
      },
      {
        "form": "αὐτοῦ",
        "lemma": "αὐτός",
        "pos": "RP",
        "morph": "----GSM-"
      },
      {
        "form": "γεγέννηται.",
        "lemma": "γεννάω",
        "pos": "V-",
        "morph": "3XPI-S--"
      }
    ]
  }
]