[
  {
    "v": 1,
    "tokens": [
      {
        "form": "Συνεργοῦντες",
        "lemma": "συνεργέω",
        "pos": "V-",
        "morph": "-PAPNPM-"
      },
      {
        "form": "δὲ",
        "lemma": "δέ",
        "pos": "C-",
        "morph": "--------"
      },
      {
        "form": "καὶ",
        "lemma": "καί",
        "pos": "D-",
        "morph": "--------"
      },
      {
        "form": "παρακαλοῦμεν",
        "lemma": "παρακαλέω",
        "pos": "V-",
        "morph": "1PAI-P--"
      },
      {
        "form": "μὴ",
        "lemma": "μή",
        "pos": "D-",
        "morph": "--------"
      },
      {
        "form": "εἰς",
        "lemma": "εἰς",
        "pos": "P-",
        "morph": "--------"
      },
      {
        "form": "κενὸν",
        "lemma": "κενός",
        "pos": "A-",
        "morph": "----ASN-"
      },
      {
        "form": "τὴν",
        "lemma": "ὁ",
        "pos": "RA",
        "morph": "----ASF-"
      },
      {
        "form": "χάριν",
        "lemma": "χάρις",
        "pos": "N-",
        "morph": "----ASF-"
      },
      {
        "form": "τοῦ",
        "lemma": "ὁ",
        "pos": "RA",
        "morph": "----GSM-"
      },
      {
        "form": "θεοῦ",
        "lemma": "θεός",
        "pos": "N-",
        "morph": "----GSM-"
      },
      {
        "form": "δέξασθαι",
        "lemma": "δέχομαι",
        "pos": "V-",
        "morph": "-AMN----"
      },
      {
        "form": "ὑμᾶς·",
        "lemma": "σύ",
        "pos": "RP",
        "morph": "----AP--"
      }
    ]
  },
  {
    "v": 2,
    "tokens": [
      {
        "form": "λέγει",
        "lemma": "λέγω",
        "pos": "V-",
        "morph": "3PAI-S--"
      },
      {
        "form": "γάρ·",
        "lemma": "γάρ",
        "pos": "C-",
        "morph": "--------"
      },
      {
        "form": "Καιρῷ",
        "lemma": "καιρός",
        "pos": "N-",
        "morph": "----DSM-"
      },
      {
        "form": "δεκτῷ",
        "lemma": "δεκτός",
        "pos": "A-",
        "morph": "----DSM-"
      },
      {
        "form": "ἐπήκουσά",
        "lemma": "ἐπακούω",
        "pos": "V-",
        "morph": "1AAI-S--"
      },
      {
        "form": "σου",
        "lemma": "σύ",
        "pos": "RP",
        "morph": "----GS--"
      },
      {
        "form": "καὶ",
        "lemma": "καί",
        "pos": "C-",
        "morph": "--------"
      },
      {
        "form": "ἐν",
        "lemma": "ἐν",
        "pos": "P-",
        "morph": "--------"
      },
      {
        "form": "ἡμέρᾳ",
        "lemma": "ἡμέρα",
        "pos": "N-",
        "morph": "----DSF-"
      },
      {
        "form": "σωτηρίας",
        "lemma": "σωτηρία",
        "pos": "N-",
        "morph": "----GSF-"
      },
      {
        "form": "ἐβοήθησά",
        "lemma": "βοηθέω",
        "pos": "V-",
        "morph": "1AAI-S--"
      },
      {
        "form": "σοι·",
        "lemma": "σύ",
        "pos": "RP",
        "morph": "----DS--"
      },
      {
        "form": "ἰδοὺ",
        "lemma": "ἰδού",
        "pos": "X-",
        "morph": "--------"
      },
      {
        "form": "νῦν",
        "lemma": "νῦν",
        "pos": "D-",
        "morph": "--------"
      },
      {
        "form": "καιρὸς",
        "lemma": "καιρός",
        "pos": "N-",
        "morph": "----NSM-"
      },
      {
        "form": "εὐπρόσδεκτος,",
        "lemma": "εὐπρόσδεκτος",
        "pos": "A-",
        "morph": "----NSM-"
      },
      {
        "form": "ἰδοὺ",
        "lemma": "ἰδού",
        "pos": "X-",
        "morph": "--------"
      },
      {
        "form": "νῦν",
        "lemma": "νῦν",
        "pos": "D-",
        "morph": "--------"
      },
      {
        "form": "ἡμέρα",
        "lemma": "ἡμέρα",
        "pos": "N-",
        "morph": "----NSF-"
      },
      {
        "form": "σωτηρίας·",
        "lemma": "σωτηρία",
        "pos": "N-",
        "morph": "----GSF-"
      }
    ]
  },
  {
    "v": 3,
    "tokens": [
      {
        "form": "μηδεμίαν",
        "lemma": "μηδείς",
        "pos": "A-",
        "morph": "----ASF-"
      },
      {
        "form": "ἐν",
        "lemma": "ἐν",
        "pos": "P-",
        "morph": "--------"
      },
      {
        "form": "μηδενὶ",
        "lemma": "μηδείς",
        "pos": "A-",
        "morph": "----DSM-"
      },
      {
        "form": "διδόντες",
        "lemma": "δίδωμι",
        "pos": "V-",
        "morph": "-PAPNPM-"
      },
      {
        "form": "προσκοπήν,",
        "lemma": "προσκοπή",
        "pos": "N-",
        "morph": "----ASF-"
      },
      {
        "form": "ἵνα",
        "lemma": "ἵνα",
        "pos": "C-",
        "morph": "--------"
      },
      {
        "form": "μὴ",
        "lemma": "μή",
        "pos": "D-",
        "morph": "--------"
      },
      {
        "form": "μωμηθῇ",
        "lemma": "μωμάομαι",
        "pos": "V-",
        "morph": "3APS-S--"
      },
      {
        "form": "ἡ",
        "lemma": "ὁ",
        "pos": "RA",
        "morph": "----NSF-"
      },
      {
        "form": "διακονία,",
        "lemma": "διακονία",
        "pos": "N-",
        "morph": "----NSF-"
      }
    ]
  },
  {
    "v": 4,
    "tokens": [
      {
        "form": "ἀλλ’",
        "lemma": "ἀλλά",
        "pos": "C-",
        "morph": "--------"
      },
      {
        "form": "ἐν",
        "lemma": "ἐν",
        "pos": "P-",
        "morph": "--------"
      },
      {
        "form": "παντὶ",
        "lemma": "πᾶς",
        "pos": "A-",
        "morph": "----DSN-"
      },
      {
        "form": "⸀συνιστάνοντες",
        "lemma": "συνίστημι",
        "pos": "V-",
        "morph": "-PAPNPM-"
      },
      {
        "form": "ἑαυτοὺς",
        "lemma": "ἑαυτοῦ",
        "pos": "RP",
        "morph": "----APM-"
      },
      {
        "form": "ὡς",
        "lemma": "ὡς",
        "pos": "C-",
        "morph": "--------"
      },
      {
        "form": "θεοῦ",
        "lemma": "θεός",
        "pos": "N-",
        "morph": "----GSM-"
      },
      {
        "form": "διάκονοι·",
        "lemma": "διάκονος",
        "pos": "N-",
        "morph": "----NPM-"
      },
      {
        "form": "ἐν",
        "lemma": "ἐν",
        "pos": "P-",
        "morph": "--------"
      },
      {
        "form": "ὑπομονῇ",
        "lemma": "ὑπομονή",
        "pos": "N-",
        "morph": "----DSF-"
      },
      {
        "form": "πολλῇ,",
        "lemma": "πολύς",
        "pos": "A-",
        "morph": "----DSF-"
      },
      {
        "form": "ἐν",
        "lemma": "ἐν",
        "pos": "P-",
        "morph": "--------"
      },
      {
        "form": "θλίψεσιν,",
        "lemma": "θλῖψις",
        "pos": "N-",
        "morph": "----DPF-"
      },
      {
        "form": "ἐν",
        "lemma": "ἐν",
        "pos": "P-",
        "morph": "--------"
      },
      {
        "form": "ἀνάγκαις,",
        "lemma": "ἀνάγκη",
        "pos": "N-",
        "morph": "----DPF-"
      },
      {
        "form": "ἐν",
        "lemma": "ἐν",
        "pos": "P-",
        "morph": "--------"
      },
      {
        "form": "στενοχωρίαις,",
        "lemma": "στενοχωρία",
        "pos": "N-",
        "morph": "----DPF-"
      }
    ]
  },
  {
    "v": 5,
    "tokens": [
      {
        "form": "ἐν",
        "lemma": "ἐν",
        "pos": "P-",
        "morph": "--------"
      },
      {
        "form": "πληγαῖς,",
        "lemma": "πληγή",
        "pos": "N-",
        "morph": "----DPF-"
      },
      {
        "form": "ἐν",
        "lemma": "ἐν",
        "pos": "P-",
        "morph": "--------"
      },
      {
        "form": "φυλακαῖς,",
        "lemma": "φυλακή",
        "pos": "N-",
        "morph": "----DPF-"
      },
      {
        "form": "ἐν",
        "lemma": "ἐν",
        "pos": "P-",
        "morph": "--------"
      },
      {
        "form": "ἀκαταστασίαις,",
        "lemma": "ἀκαταστασία",
        "pos": "N-",
        "morph": "----DPF-"
      },
      {
        "form": "ἐν",
        "lemma": "ἐν",
        "pos": "P-",
        "morph": "--------"
      },
      {
        "form": "κόποις,",
        "lemma": "κόπος",
        "pos": "N-",
        "morph": "----DPM-"
      },
      {
        "form": "ἐν",
        "lemma": "ἐν",
        "pos": "P-",
        "morph": "--------"
      },
      {
        "form": "ἀγρυπνίαις,",
        "lemma": "ἀγρυπνία",
        "pos": "N-",
        "morph": "----DPF-"
      },
      {
        "form": "ἐν",
        "lemma": "ἐν",
        "pos": "P-",
        "morph": "--------"
      },
      {
        "form": "νηστείαις,",
        "lemma": "νηστεία",
        "pos": "N-",
        "morph": "----DPF-"
      }
    ]
  },
  {
    "v": 6,
    "tokens": [
      {
        "form": "ἐν",
        "lemma": "ἐν",
        "pos": "P-",
        "morph": "--------"
      },
      {
        "form": "ἁγνότητι,",
        "lemma": "ἁγνότης",
        "pos": "N-",
        "morph": "----DSF-"
      },
      {
        "form": "ἐν",
        "lemma": "ἐν",
        "pos": "P-",
        "morph": "--------"
      },
      {
        "form": "γνώσει,",
        "lemma": "γνῶσις",
        "pos": "N-",
        "morph": "----DSF-"
      },
      {
        "form": "ἐν",
        "lemma": "ἐν",
        "pos": "P-",
        "morph": "--------"
      },
      {
        "form": "μακροθυμίᾳ,",
        "lemma": "μακροθυμία",
        "pos": "N-",
        "morph": "----DSF-"
      },
      {
        "form": "ἐν",
        "lemma": "ἐν",
        "pos": "P-",
        "morph": "--------"
      },
      {
        "form": "χρηστότητι,",
        "lemma": "χρηστότης",
        "pos": "N-",
        "morph": "----DSF-"
      },
      {
        "form": "ἐν",
        "lemma": "ἐν",
        "pos": "P-",
        "morph": "--------"
      },
      {
        "form": "πνεύματι",
        "lemma": "πνεῦμα",
        "pos": "N-",
        "morph": "----DSN-"
      },
      {
        "form": "ἁγίῳ,",
        "lemma": "ἅγιος",
        "pos": "A-",
        "morph": "----DSN-"
      },
      {
        "form": "ἐν",
        "lemma": "ἐν",
        "pos": "P-",
        "morph": "--------"
      },
      {
        "form": "ἀγάπῃ",
        "lemma": "ἀγάπη",
        "pos": "N-",
        "morph": "----DSF-"
      },
      {
        "form": "ἀνυποκρίτῳ,",
        "lemma": "ἀνυπόκριτος",
        "pos": "A-",
        "morph": "----DSF-"
      }
    ]
  },
  {
    "v": 7,
    "tokens": [
      {
        "form": "ἐν",
        "lemma": "ἐν",
        "pos": "P-",
        "morph": "--------"
      },
      {
        "form": "λόγῳ",
        "lemma": "λόγος",
        "pos": "N-",
        "morph": "----DSM-"
      },
      {
        "form": "ἀληθείας,",
        "lemma": "ἀλήθεια",
        "pos": "N-",
        "morph": "----GSF-"
      },
      {
        "form": "ἐν",
        "lemma": "ἐν",
        "pos": "P-",
        "morph": "--------"
      },
      {
        "form": "δυνάμει",
        "lemma": "δύναμις",
        "pos": "N-",
        "morph": "----DSF-"
      },
      {
        "form": "θεοῦ·",
        "lemma": "θεός",
        "pos": "N-",
        "morph": "----GSM-"
      },
      {
        "form": "διὰ",
        "lemma": "διά",
        "pos": "P-",
        "morph": "--------"
      },
      {
        "form": "τῶν",
        "lemma": "ὁ",
        "pos": "RA",
        "morph": "----GPN-"
      },
      {
        "form": "ὅπλων",
        "lemma": "ὅπλον",
        "pos": "N-",
        "morph": "----GPN-"
      },
      {
        "form": "τῆς",
        "lemma": "ὁ",
        "pos": "RA",
        "morph": "----GSF-"
      },
      {
        "form": "δικαιοσύνης",
        "lemma": "δικαιοσύνη",
        "pos": "N-",
        "morph": "----GSF-"
      },
      {
        "form": "τῶν",
        "lemma": "ὁ",
        "pos": "RA",
        "morph": "----GPN-"
      },
      {
        "form": "δεξιῶν",
        "lemma": "δεξιός",
        "pos": "A-",
        "morph": "----GPN-"
      },
      {
        "form": "καὶ",
        "lemma": "καί",
        "pos": "C-",
        "morph": "--------"
      },
      {
        "form": "ἀριστερῶν,",
        "lemma": "ἀριστερός",
        "pos": "A-",
        "morph": "----GPN-"
      }
    ]
  },
  {
    "v": 8,
    "tokens": [
      {
        "form": "διὰ",
        "lemma": "διά",
        "pos": "P-",
        "morph": "--------"
      },
      {
        "form": "δόξης",
        "lemma": "δόξα",
        "pos": "N-",
        "morph": "----GSF-"
      },
      {
        "form": "καὶ",
        "lemma": "καί",
        "pos": "C-",
        "morph": "--------"
      },
      {
        "form": "ἀτιμίας,",
        "lemma": "ἀτιμία",
        "pos": "N-",
        "morph": "----GSF-"
      },
      {
        "form": "διὰ",
        "lemma": "διά",
        "pos": "P-",
        "morph": "--------"
      },
      {
        "form": "δυσφημίας",
        "lemma": "δυσφημία",
        "pos": "N-",
        "morph": "----GSF-"
      },
      {
        "form": "καὶ",
        "lemma": "καί",
        "pos": "C-",
        "morph": "--------"
      },
      {
        "form": "εὐφημίας·",
        "lemma": "εὐφημία",
        "pos": "N-",
        "morph": "----GSF-"
      },
      {
        "form": "ὡς",
        "lemma": "ὡς",
        "pos": "C-",
        "morph": "--------"
      },
      {
        "form": "πλάνοι",
        "lemma": "πλάνος",
        "pos": "A-",
        "morph": "----NPM-"
      },
      {
        "form": "καὶ",
        "lemma": "καί",
        "pos": "C-",
        "morph": "--------"
      },
      {
        "form": "ἀληθεῖς,",
        "lemma": "ἀληθής",
        "pos": "A-",
        "morph": "----NPM-"
      }
    ]
  },
  {
    "v": 9,
    "tokens": [
      {
        "form": "ὡς",
        "lemma": "ὡς",
        "pos": "C-",
        "morph": "--------"
      },
      {
        "form": "ἀγνοούμενοι",
        "lemma": "ἀγνοέω",
        "pos": "V-",
        "morph": "-PPPNPM-"
      },
      {
        "form": "καὶ",
        "lemma": "καί",
        "pos": "C-",
        "morph": "--------"
      },
      {
        "form": "ἐπιγινωσκόμενοι,",
        "lemma": "ἐπιγινώσκω",
        "pos": "V-",
        "morph": "-PPPNPM-"
      },
      {
        "form": "ὡς",
        "lemma": "ὡς",
        "pos": "C-",
        "morph": "--------"
      },
      {
        "form": "ἀποθνῄσκοντες",
        "lemma": "ἀποθνῄσκω",
        "pos": "V-",
        "morph": "-PAPNPM-"
      },
      {
        "form": "καὶ",
        "lemma": "καί",
        "pos": "C-",
        "morph": "--------"
      },
      {
        "form": "ἰδοὺ",
        "lemma": "ἰδού",
        "pos": "X-",
        "morph": "--------"
      },
      {
        "form": "ζῶμεν,",
        "lemma": "ζάω",
        "pos": "V-",
        "morph": "1PAI-P--"
      },
      {
        "form": "ὡς",
        "lemma": "ὡς",
        "pos": "C-",
        "morph": "--------"
      },
      {
        "form": "παιδευόμενοι",
        "lemma": "παιδεύω",
        "pos": "V-",
        "morph": "-PPPNPM-"
      },
      {
        "form": "καὶ",
        "lemma": "καί",
        "pos": "C-",
        "morph": "--------"
      },
      {
        "form": "μὴ",
        "lemma": "μή",
        "pos": "D-",
        "morph": "--------"
      },
      {
        "form": "θανατούμενοι,",
        "lemma": "θανατόω",
        "pos": "V-",
        "morph": "-PPPNPM-"
      }
    ]
  },
  {
    "v": 10,
    "tokens": [
      {
        "form": "ὡς",
        "lemma": "ὡς",
        "pos": "C-",
        "morph": "--------"
      },
      {
        "form": "λυπούμενοι",
        "lemma": "λυπέω",
        "pos": "V-",
        "morph": "-PPPNPM-"
      },
      {
        "form": "ἀεὶ",
        "lemma": "ἀεί",
        "pos": "D-",
        "morph": "--------"
      },
      {
        "form": "δὲ",
        "lemma": "δέ",
        "pos": "C-",
        "morph": "--------"
      },
      {
        "form": "χαίροντες,",
        "lemma": "χαίρω",
        "pos": "V-",
        "morph": "-PAPNPM-"
      },
      {
        "form": "ὡς",
        "lemma": "ὡς",
        "pos": "C-",
        "morph": "--------"
      },
      {
        "form": "πτωχοὶ",
        "lemma": "πτωχός",
        "pos": "A-",
        "morph": "----NPM-"
      },
      {
        "form": "πολλοὺς",
        "lemma": "πολύς",
        "pos": "A-",
        "morph": "----APM-"
      },
      {
        "form": "δὲ",
        "lemma": "δέ",
        "pos": "C-",
        "morph": "--------"
      },
      {
        "form": "πλουτίζοντες,",
        "lemma": "πλουτίζω",
        "pos": "V-",
        "morph": "-PAPNPM-"
      },
      {
        "form": "ὡς",
        "lemma": "ὡς",
        "pos": "C-",
        "morph": "--------"
      },
      {
        "form": "μηδὲν",
        "lemma": "μηδείς",
        "pos": "A-",
        "morph": "----ASN-"
      },
      {
        "form": "ἔχοντες",
        "lemma": "ἔχω",
        "pos": "V-",
        "morph": "-PAPNPM-"
      },
      {
        "form": "καὶ",
        "lemma": "καί",
        "pos": "C-",
        "morph": "--------"
      },
      {
        "form": "πάντα",
        "lemma": "πᾶς",
        "pos": "A-",
        "morph": "----APN-"
      },
      {
        "form": "κατέχοντες.",
        "lemma": "κατέχω",
        "pos": "V-",
        "morph": "-PAPNPM-"
      }
    ]
  },
  {
    "v": 11,
    "tokens": [
      {
        "form": "Τὸ",
        "lemma": "ὁ",
        "pos": "RA",
        "morph": "----NSN-"
      },
      {
        "form": "στόμα",
        "lemma": "στόμα",
        "pos": "N-",
        "morph": "----NSN-"
      },
      {
        "form": "ἡμῶν",
        "lemma": "ἐγώ",
        "pos": "RP",
        "morph": "----GP--"
      },
      {
        "form": "ἀνέῳγεν",
        "lemma": "ἀνοίγω",
        "pos": "V-",
        "morph": "3XAI-S--"
      },
      {
        "form": "πρὸς",
        "lemma": "πρός",
        "pos": "P-",
        "morph": "--------"
      },
      {
        "form": "ὑμᾶς,",
        "lemma": "σύ",
        "pos": "RP",
        "morph": "----AP--"
      },
      {
        "form": "Κορίνθιοι,",
        "lemma": "Κορίνθιος",
        "pos": "N-",
        "morph": "----VPM-"
      },
      {
        "form": "ἡ",
        "lemma": "ὁ",
        "pos": "RA",
        "morph": "----NSF-"
      },
      {
        "form": "καρδία",
        "lemma": "καρδία",
        "pos": "N-",
        "morph": "----NSF-"
      },
      {
        "form": "ἡμῶν",
        "lemma": "ἐγώ",
        "pos": "RP",
        "morph": "----GP--"
      },
      {
        "form": "πεπλάτυνται·",
        "lemma": "πλατύνω",
        "pos": "V-",
        "morph": "3XPI-S--"
      }
    ]
  },
  {
    "v": 12,
    "tokens": [
      {
        "form": "οὐ",
        "lemma": "οὐ",
        "pos": "D-",
        "morph": "--------"
      },
      {
        "form": "στενοχωρεῖσθε",
        "lemma": "στενοχωρέομαι",
        "pos": "V-",
        "morph": "2PPI-P--"
      },
      {
        "form": "ἐν",
        "lemma": "ἐν",
        "pos": "P-",
        "morph": "--------"
      },
      {
        "form": "ἡμῖν,",
        "lemma": "ἐγώ",
        "pos": "RP",
        "morph": "----DP--"
      },
      {
        "form": "στενοχωρεῖσθε",
        "lemma": "στενοχωρέομαι",
        "pos": "V-",
        "morph": "2PPI-P--"
      },
      {
        "form": "δὲ",
        "lemma": "δέ",
        "pos": "C-",
        "morph": "--------"
      },
      {
        "form": "ἐν",
        "lemma": "ἐν",
        "pos": "P-",
        "morph": "--------"
      },
      {
        "form": "τοῖς",
        "lemma": "ὁ",
        "pos": "RA",
        "morph": "----DPN-"
      },
      {
        "form": "σπλάγχνοις",
        "lemma": "σπλάγχνον",
        "pos": "N-",
        "morph": "----DPN-"
      },
      {
        "form": "ὑμῶν·",
        "lemma": "σύ",
        "pos": "RP",
        "morph": "----GP--"
      }
    ]
  },
  {
    "v": 13,
    "tokens": [
      {
        "form": "τὴν",
        "lemma": "ὁ",
        "pos": "RA",
        "morph": "----ASF-"
      },
      {
        "form": "δὲ",
        "lemma": "δέ",
        "pos": "C-",
        "morph": "--------"
      },
      {
        "form": "αὐτὴν",
        "lemma": "αὐτός",
        "pos": "A-",
        "morph": "----ASF-"
      },
      {
        "form": "ἀντιμισθίαν,",
        "lemma": "ἀντιμισθία",
        "pos": "N-",
        "morph": "----ASF-"
      },
      {
        "form": "ὡς",
        "lemma": "ὡς",
        "pos": "C-",
        "morph": "--------"
      },
      {
        "form": "τέκνοις",
        "lemma": "τέκνον",
        "pos": "N-",
        "morph": "----DPN-"
      },
      {
        "form": "λέγω,",
        "lemma": "λέγω",
        "pos": "V-",
        "morph": "1PAI-S--"
      },
      {
        "form": "πλατύνθητε",
        "lemma": "πλατύνω",
        "pos": "V-",
        "morph": "2APD-P--"
      },
      {
        "form": "καὶ",
        "lemma": "καί",
        "pos": "D-",
        "morph": "--------"
      },
      {
        "form": "ὑμεῖς.",
        "lemma": "σύ",
        "pos": "RP",
        "morph": "----NP--"
      }
    ]
  },
  {
    "v": 14,
    "tokens": [
      {
        "form": "Μὴ",
        "lemma": "μή",
        "pos": "D-",
        "morph": "--------"
      },
      {
        "form": "γίνεσθε",
        "lemma": "γίνομαι",
        "pos": "V-",
        "morph": "2PMD-P--"
      },
      {
        "form": "ἑτεροζυγοῦντες",
        "lemma": "ἑτεροζυγέω",
        "pos": "V-",
        "morph": "-PAPNPM-"
      },
      {
        "form": "ἀπίστοις·",
        "lemma": "ἄπιστος",
        "pos": "A-",
        "morph": "----DPM-"
      },
      {
        "form": "τίς",
        "lemma": "τίς",
        "pos": "RI",
        "morph": "----NSF-"
      },
      {
        "form": "γὰρ",
        "lemma": "γάρ",
        "pos": "C-",
        "morph": "--------"
      },
      {
        "form": "μετοχὴ",
        "lemma": "μετοχή",
        "pos": "N-",
        "morph": "----NSF-"
      },
      {
        "form": "δικαιοσύνῃ",
        "lemma": "δικαιοσύνη",
        "pos": "N-",
        "morph": "----DSF-"
      },
      {
        "form": "καὶ",
        "lemma": "καί",
        "pos": "C-",
        "morph": "--------"
      },
      {
        "form": "ἀνομίᾳ,",
        "lemma": "ἀνομία",
        "pos": "N-",
        "morph": "----DSF-"
      },
      {
        "form": "⸂ἢ",
        "lemma": "ἤ",
        "pos": "C-",
        "morph": "--------"
      },
      {
        "form": "τίς⸃",
        "lemma": "τίς",
        "pos": "RI",
        "morph": "----NSF-"
      },
      {
        "form": "κοινωνία",
        "lemma": "κοινωνία",
        "pos": "N-",
        "morph": "----NSF-"
      },
      {
        "form": "φωτὶ",
        "lemma": "φῶς",
        "pos": "N-",
        "morph": "----DSN-"
      },
      {
        "form": "πρὸς",
        "lemma": "πρός",
        "pos": "P-",
        "morph": "--------"
      },
      {
        "form": "σκότος;",
        "lemma": "σκότος",
        "pos": "N-",
        "morph": "----ASN-"
      }
    ]
  },
  {
    "v": 15,
    "tokens": [
      {
        "form": "τίς",
        "lemma": "τίς",
        "pos": "RI",
        "morph": "----NSF-"
      },
      {
        "form": "δὲ",
        "lemma": "δέ",
        "pos": "C-",
        "morph": "--------"
      },
      {
        "form": "συμφώνησις",
        "lemma": "συμφώνησις",
        "pos": "N-",
        "morph": "----NSF-"
      },
      {
        "form": "⸀Χριστοῦ",
        "lemma": "Χριστός",
        "pos": "N-",
        "morph": "----GSM-"
      },
      {
        "form": "πρὸς",
        "lemma": "πρός",
        "pos": "P-",
        "morph": "--------"
      },
      {
        "form": "Βελιάρ,",
        "lemma": "Βελιάρ",
        "pos": "N-",
        "morph": "----ASM-"
      },
      {
        "form": "ἢ",
        "lemma": "ἤ",
        "pos": "C-",
        "morph": "--------"
      },
      {
        "form": "τίς",
        "lemma": "τίς",
        "pos": "RI",
        "morph": "----NSF-"
      },
      {
        "form": "μερὶς",
        "lemma": "μερίς",
        "pos": "N-",
        "morph": "----NSF-"
      },
      {
        "form": "πιστῷ",
        "lemma": "πιστός",
        "pos": "A-",
        "morph": "----DSM-"
      },
      {
        "form": "μετὰ",
        "lemma": "μετά",
        "pos": "P-",
        "morph": "--------"
      },
      {
        "form": "ἀπίστου;",
        "lemma": "ἄπιστος",
        "pos": "A-",
        "morph": "----GSM-"
      }
    ]
  },
  {
    "v": 16,
    "tokens": [
      {
        "form": "τίς",
        "lemma": "τίς",
        "pos": "RI",
        "morph": "----NSF-"
      },
      {
        "form": "δὲ",
        "lemma": "δέ",
        "pos": "C-",
        "morph": "--------"
      },
      {
        "form": "συγκατάθεσις",
        "lemma": "συγκατάθεσις",
        "pos": "N-",
        "morph": "----NSF-"
      },
      {
        "form": "ναῷ",
        "lemma": "ναός",
        "pos": "N-",
        "morph": "----DSM-"
      },
      {
        "form": "θεοῦ",
        "lemma": "θεός",
        "pos": "N-",
        "morph": "----GSM-"
      },
      {
        "form": "μετὰ",
        "lemma": "μετά",
        "pos": "P-",
        "morph": "--------"
      },
      {
        "form": "εἰδώλων;",
        "lemma": "εἴδωλον",
        "pos": "N-",
        "morph": "----GPN-"
      },
      {
        "form": "⸂ἡμεῖς",
        "lemma": "ἐγώ",
        "pos": "RP",
        "morph": "----NP--"
      },
      {
        "form": "γὰρ",
        "lemma": "γάρ",
        "pos": "C-",
        "morph": "--------"
      },
      {
        "form": "ναὸς",
        "lemma": "ναός",
        "pos": "N-",
        "morph": "----NSM-"
      },
      {
        "form": "θεοῦ",
        "lemma": "θεός",
        "pos": "N-",
        "morph": "----GSM-"
      },
      {
        "form": "ἐσμεν⸃",
        "lemma": "εἰμί",
        "pos": "V-",
        "morph": "1PAI-P--"
      },
      {
        "form": "ζῶντος·",
        "lemma": "ζάω",
        "pos": "V-",
        "morph": "-PAPGSM-"
      },
      {
        "form": "καθὼς",
        "lemma": "καθώς",
        "pos": "C-",
        "morph": "--------"
      },
      {
        "form": "εἶπεν",
        "lemma": "λέγω",
        "pos": "V-",
        "morph": "3AAI-S--"
      },
      {
        "form": "ὁ",
        "lemma": "ὁ",
        "pos": "RA",
        "morph": "----NSM-"
      },
      {
        "form": "θεὸς",
        "lemma": "θεός",
        "pos": "N-",
        "morph": "----NSM-"
      },
      {
        "form": "ὅτι",
        "lemma": "ὅτι",
        "pos": "C-",
        "morph": "--------"
      },
      {
        "form": "Ἐνοικήσω",
        "lemma": "ἐνοικέω",
        "pos": "V-",
        "morph": "1FAI-S--"
      },
      {
        "form": "ἐν",
        "lemma": "ἐν",
        "pos": "P-",
        "morph": "--------"
      },
      {
        "form": "αὐτοῖς",
        "lemma": "αὐτός",
        "pos": "RP",
        "morph": "----DPM-"
      },
      {
        "form": "καὶ",
        "lemma": "καί",
        "pos": "C-",
        "morph": "--------"
      },
      {
        "form": "ἐμπεριπατήσω,",
        "lemma": "ἐμπεριπατέω",
        "pos": "V-",
        "morph": "1FAI-S--"
      },
      {
        "form": "καὶ",
        "lemma": "καί",
        "pos": "C-",
        "morph": "--------"
      },
      {
        "form": "ἔσομαι",
        "lemma": "εἰμί",
        "pos": "V-",
        "morph": "1FMI-S--"
      },
      {
        "form": "αὐτῶν",
        "lemma": "αὐτός",
        "pos": "RP",
        "morph": "----GPM-"
      },
      {
        "form": "θεός,",
        "lemma": "θεός",
        "pos": "N-",
        "morph": "----NSM-"
      },
      {
        "form": "καὶ",
        "lemma": "καί",
        "pos": "C-",
        "morph": "--------"
      },
      {
        "form": "αὐτοὶ",
        "lemma": "αὐτός",
        "pos": "RP",
        "morph": "----NPM-"
      },
      {
        "form": "ἔσονταί",
        "lemma": "εἰμί",
        "pos": "V-",
        "morph": "3FMI-P--"
      },
      {
        "form": "⸀μου",
        "lemma": "ἐγώ",
        "pos": "RP",
        "morph": "----GS--"
      },
      {
        "form": "λαός.",
        "lemma": "λαός",
        "pos": "N-",
        "morph": "----NSM-"
      }
    ]
  },
  {
    "v": 17,
    "tokens": [
      {
        "form": "διὸ",
        "lemma": "διό",
        "pos": "C-",
        "morph": "--------"
      },
      {
        "form": "ἐξέλθατε",
        "lemma": "ἐξέρχομαι",
        "pos": "V-",
        "morph": "2AAD-P--"
      },
      {
        "form": "ἐκ",
        "lemma": "ἐκ",
        "pos": "P-",
        "morph": "--------"
      },
      {
        "form": "μέσου",
        "lemma": "μέσος",
        "pos": "A-",
        "morph": "----GSN-"
      },
      {
        "form": "αὐτῶν,",
        "lemma": "αὐτός",
        "pos": "RP",
        "morph": "----GPM-"
      },
      {
        "form": "καὶ",
        "lemma": "καί",
        "pos": "C-",
        "morph": "--------"
      },
      {
        "form": "ἀφορίσθητε,",
        "lemma": "ἀφορίζω",
        "pos": "V-",
        "morph": "2APD-P--"
      },
      {
        "form": "λέγει",
        "lemma": "λέγω",
        "pos": "V-",
        "morph": "3PAI-S--"
      },
      {
        "form": "κύριος,",
        "lemma": "κύριος",
        "pos": "N-",
        "morph": "----NSM-"
      },
      {
        "form": "καὶ",
        "lemma": "καί",
        "pos": "C-",
        "morph": "--------"
      },
      {
        "form": "ἀκαθάρτου",
        "lemma": "ἀκάθαρτος",
        "pos": "A-",
        "morph": "----GSN-"
      },
      {
        "form": "μὴ",
        "lemma": "μή",
        "pos": "D-",
        "morph": "--------"
      },
      {
        "form": "ἅπτεσθε·",
        "lemma": "ἅπτω",
        "pos": "V-",
        "morph": "2PMD-P--"
      },
      {
        "form": "κἀγὼ",
        "lemma": "κἀγώ",
        "pos": "RP",
        "morph": "----NS--"
      },
      {
        "form": "εἰσδέξομαι",
        "lemma": "εἰσδέχομαι",
        "pos": "V-",
        "morph": "1FMI-S--"
      },
      {
        "form": "ὑμᾶς·",
        "lemma": "σύ",
        "pos": "RP",
        "morph": "----AP--"
      }
    ]
  },
  {
    "v": 18,
    "tokens": [
      {
        "form": "καὶ",
        "lemma": "καί",
        "pos": "C-",
        "morph": "--------"
      },
      {
        "form": "ἔσομαι",
        "lemma": "εἰμί",
        "pos": "V-",
        "morph": "1FMI-S--"
      },
      {
        "form": "ὑμῖν",
        "lemma": "σύ",
        "pos": "RP",
        "morph": "----DP--"
      },
      {
        "form": "εἰς",
        "lemma": "εἰς",
        "pos": "P-",
        "morph": "--------"
      },
      {
        "form": "πατέρα,",
        "lemma": "πατήρ",
        "pos": "N-",
        "morph": "----ASM-"
      },
      {
        "form": "καὶ",
        "lemma": "καί",
        "pos": "C-",
        "morph": "--------"
      },
      {
        "form": "ὑμεῖς",
        "lemma": "σύ",
        "pos": "RP",
        "morph": "----NP--"
      },
      {
        "form": "ἔσεσθέ",
        "lemma": "εἰμί",
        "pos": "V-",
        "morph": "2FMI-P--"
      },
      {
        "form": "μοι",
        "lemma": "ἐγώ",
        "pos": "RP",
        "morph": "----DS--"
      },
      {
        "form": "εἰς",
        "lemma": "εἰς",
        "pos": "P-",
        "morph": "--------"
      },
      {
        "form": "υἱοὺς",
        "lemma": "υἱός",
        "pos": "N-",
        "morph": "----APM-"
      },
      {
        "form": "καὶ",
        "lemma": "καί",
        "pos": "C-",
        "morph": "--------"
      },
      {
        "form": "θυγατέρας,",
        "lemma": "θυγάτηρ",
        "pos": "N-",
        "morph": "----APF-"
      },
      {
        "form": "λέγει",
        "lemma": "λέγω",
        "pos": "V-",
        "morph": "3PAI-S--"
      },
      {
        "form": "κύριος",
        "lemma": "κύριος",
        "pos": "N-",
        "morph": "----NSM-"
      },
      {
        "form": "παντοκράτωρ.",
        "lemma": "παντοκράτωρ",
        "pos": "N-",
        "morph": "----NSM-"
      }
    ]
  }
]